<worksheet xmlns="http://schemas.openxmlformats.org/spreadsheetml/2006/main"><sheetPr><outlinePr summaryBelow="1" summaryRight="1"/><pageSetUpPr/></sheetPr><dimension ref="A1:H65"/><sheetViews><sheetView workbookViewId="0"><selection activeCell="A1" sqref="A1"/></sheetView></sheetViews><sheetFormatPr baseColWidth="8" defaultRowHeight="15"/><cols><col width="24" customWidth="1" min="1" max="1"/><col width="90" customWidth="1" min="2" max="2"/><col width="16" customWidth="1" min="4" max="4"/><col width="28" customWidth="1" min="5" max="5"/></cols><sheetData><row r="1"><c r="A1" s="1" t="inlineStr"><is><t>ESTIMATE BUILDER (Client Output)</t></is></c></row><row r="3"><c r="A3" s="9" t="inlineStr"><is><t>JobID</t></is></c><c r="B3" s="8"><f>'Job Control'!$B$3</f><v></v></c></row><row r="5"><c r="A5" s="5" t="inlineStr"><is><t>Room</t></is></c><c r="B5" s="5" t="inlineStr"><is><t>Description</t></is></c><c r="D5" s="5" t="inlineStr"><is><t>Paints (job-level)</t></is></c></row><row r="6"><c r="A6" s="6"><f>IFERROR(INDEX(FILTER(INPUT_Rooms!$C$4:$C$83, INPUT_Rooms!$A$4:$A$83=$B$3), 1), "")</f><v></v></c><c r="B6" s="6"><f>IF(A6="","",TEXTJOIN(" ",TRUE,IF(INDEX(FILTER(INPUT_Rooms!$K$4:$K$83, INPUT_Rooms!$A$4:$A$83=$B$3),1)="Y","Prep and paint "&amp;INDEX(FILTER(INPUT_Rooms!$M$4:$M$83, INPUT_Rooms!$A$4:$A$83=$B$3),1)&amp;" coat(s) on "&amp;A6&amp;" walls.", ""),IF(INDEX(FILTER(INPUT_Rooms!$O$4:$O$83, INPUT_Rooms!$A$4:$A$83=$B$3),1)="Y","Prep and paint "&amp;INDEX(FILTER(INPUT_Rooms!$Q$4:$Q$83, INPUT_Rooms!$A$4:$A$83=$B$3),1)&amp;" coat(s) on "&amp;A6&amp;" ceilings.", ""),IF(INDEX(FILTER(INPUT_Rooms!$T$4:$T$83, INPUT_Rooms!$A$4:$A$83=$B$3),1)="Y","Prep and paint "&amp;INDEX(FILTER(INPUT_Rooms!$V$4:$V$83, INPUT_Rooms!$A$4:$A$83=$B$3),1)&amp;" coat(s) on "&amp;A6&amp;" trim ("&amp;TEXTJOIN(", ",TRUE,IF(INDEX(FILTER(INPUT_Rooms!$X$4:$X$83, INPUT_Rooms!$A$4:$A$83=$B$3),1)="Y","base",""),IF(INDEX(FILTER(INPUT_Rooms!$Y$4:$Y$83, INPUT_Rooms!$A$4:$A$83=$B$3),1)="Y","crown",""),IF(INDEX(FILTER(INPUT_Rooms!$Z$4:$Z$83, INPUT_Rooms!$A$4:$A$83=$B$3),1)="Y","window casing",""),IF(INDEX(FILTER(INPUT_Rooms!$AA$4:$AA$83, INPUT_Rooms!$A$4:$A$83=$B$3),1)="Y","door casing",""),IF(INDEX(FILTER(INPUT_Rooms!$AB$4:$AB$83, INPUT_Rooms!$A$4:$A$83=$B$3),1)="Y","doors",""))&amp;").", "")))</f><v></v></c><c r="D6" s="2" t="inlineStr"><is><t>Walls:</t></is></c><c r="E6" s="3"><f>XLOOKUP('Job Control'!$B$3, INPUT_JobSettings!$A:$A, INPUT_JobSettings!$K:$K, "")</f><v></v></c></row><row r="7"><c r="A7" s="6"><f>IFERROR(INDEX(FILTER(INPUT_Rooms!$C$4:$C$83, INPUT_Rooms!$A$4:$A$83=$B$3), 2), "")</f><v></v></c><c r="B7" s="6"><f>IF(A7="","",TEXTJOIN(" ",TRUE,IF(INDEX(FILTER(INPUT_Rooms!$K$4:$K$83, INPUT_Rooms!$A$4:$A$83=$B$3),2)="Y","Prep and paint "&amp;INDEX(FILTER(INPUT_Rooms!$M$4:$M$83, INPUT_Rooms!$A$4:$A$83=$B$3),2)&amp;" coat(s) on "&amp;A7&amp;" walls.", ""),IF(INDEX(FILTER(INPUT_Rooms!$O$4:$O$83, INPUT_Rooms!$A$4:$A$83=$B$3),2)="Y","Prep and paint "&amp;INDEX(FILTER(INPUT_Rooms!$Q$4:$Q$83, INPUT_Rooms!$A$4:$A$83=$B$3),2)&amp;" coat(s) on "&amp;A7&amp;" ceilings.", ""),IF(INDEX(FILTER(INPUT_Rooms!$T$4:$T$83, INPUT_Rooms!$A$4:$A$83=$B$3),2)="Y","Prep and paint "&amp;INDEX(FILTER(INPUT_Rooms!$V$4:$V$83, INPUT_Rooms!$A$4:$A$83=$B$3),2)&amp;" coat(s) on "&amp;A7&amp;" trim ("&amp;TEXTJOIN(", ",TRUE,IF(INDEX(FILTER(INPUT_Rooms!$X$4:$X$83, INPUT_Rooms!$A$4:$A$83=$B$3),2)="Y","base",""),IF(INDEX(FILTER(INPUT_Rooms!$Y$4:$Y$83, INPUT_Rooms!$A$4:$A$83=$B$3),2)="Y","crown",""),IF(INDEX(FILTER(INPUT_Rooms!$Z$4:$Z$83, INPUT_Rooms!$A$4:$A$83=$B$3),2)="Y","window casing",""),IF(INDEX(FILTER(INPUT_Rooms!$AA$4:$AA$83, INPUT_Rooms!$A$4:$A$83=$B$3),2)="Y","door casing",""),IF(INDEX(FILTER(INPUT_Rooms!$AB$4:$AB$83, INPUT_Rooms!$A$4:$A$83=$B$3),2)="Y","doors",""))&amp;").", "")))</f><v></v></c><c r="D7" s="2" t="inlineStr"><is><t>Ceilings:</t></is></c><c r="E7" s="3"><f>XLOOKUP('Job Control'!$B$3, INPUT_JobSettings!$A:$A, INPUT_JobSettings!$L:$L, "")</f><v></v></c></row><row r="8"><c r="A8" s="6"><f>IFERROR(INDEX(FILTER(INPUT_Rooms!$C$4:$C$83, INPUT_Rooms!$A$4:$A$83=$B$3), 3), "")</f><v></v></c><c r="B8" s="6"><f>IF(A8="","",TEXTJOIN(" ",TRUE,IF(INDEX(FILTER(INPUT_Rooms!$K$4:$K$83, INPUT_Rooms!$A$4:$A$83=$B$3),3)="Y","Prep and paint "&amp;INDEX(FILTER(INPUT_Rooms!$M$4:$M$83, INPUT_Rooms!$A$4:$A$83=$B$3),3)&amp;" coat(s) on "&amp;A8&amp;" walls.", ""),IF(INDEX(FILTER(INPUT_Rooms!$O$4:$O$83, INPUT_Rooms!$A$4:$A$83=$B$3),3)="Y","Prep and paint "&amp;INDEX(FILTER(INPUT_Rooms!$Q$4:$Q$83, INPUT_Rooms!$A$4:$A$83=$B$3),3)&amp;" coat(s) on "&amp;A8&amp;" ceilings.", ""),IF(INDEX(FILTER(INPUT_Rooms!$T$4:$T$83, INPUT_Rooms!$A$4:$A$83=$B$3),3)="Y","Prep and paint "&amp;INDEX(FILTER(INPUT_Rooms!$V$4:$V$83, INPUT_Rooms!$A$4:$A$83=$B$3),3)&amp;" coat(s) on "&amp;A8&amp;" trim ("&amp;TEXTJOIN(", ",TRUE,IF(INDEX(FILTER(INPUT_Rooms!$X$4:$X$83, INPUT_Rooms!$A$4:$A$83=$B$3),3)="Y","base",""),IF(INDEX(FILTER(INPUT_Rooms!$Y$4:$Y$83, INPUT_Rooms!$A$4:$A$83=$B$3),3)="Y","crown",""),IF(INDEX(FILTER(INPUT_Rooms!$Z$4:$Z$83, INPUT_Rooms!$A$4:$A$83=$B$3),3)="Y","window casing",""),IF(INDEX(FILTER(INPUT_Rooms!$AA$4:$AA$83, INPUT_Rooms!$A$4:$A$83=$B$3),3)="Y","door casing",""),IF(INDEX(FILTER(INPUT_Rooms!$AB$4:$AB$83, INPUT_Rooms!$A$4:$A$83=$B$3),3)="Y","doors",""))&amp;").", "")))</f><v></v></c><c r="D8" s="2" t="inlineStr"><is><t>Trim:</t></is></c><c r="E8" s="3"><f>XLOOKUP('Job Control'!$B$3, INPUT_JobSettings!$A:$A, INPUT_JobSettings!$M:$M, "")</f><v></v></c></row><row r="9"><c r="A9" s="6"><f>IFERROR(INDEX(FILTER(INPUT_Rooms!$C$4:$C$83, INPUT_Rooms!$A$4:$A$83=$B$3), 4), "")</f><v></v></c><c r="B9" s="6"><f>IF(A9="","",TEXTJOIN(" ",TRUE,IF(INDEX(FILTER(INPUT_Rooms!$K$4:$K$83, INPUT_Rooms!$A$4:$A$83=$B$3),4)="Y","Prep and paint "&amp;INDEX(FILTER(INPUT_Rooms!$M$4:$M$83, INPUT_Rooms!$A$4:$A$83=$B$3),4)&amp;" coat(s) on "&amp;A9&amp;" walls.", ""),IF(INDEX(FILTER(INPUT_Rooms!$O$4:$O$83, INPUT_Rooms!$A$4:$A$83=$B$3),4)="Y","Prep and paint "&amp;INDEX(FILTER(INPUT_Rooms!$Q$4:$Q$83, INPUT_Rooms!$A$4:$A$83=$B$3),4)&amp;" coat(s) on "&amp;A9&amp;" ceilings.", ""),IF(INDEX(FILTER(INPUT_Rooms!$T$4:$T$83, INPUT_Rooms!$A$4:$A$83=$B$3),4)="Y","Prep and paint "&amp;INDEX(FILTER(INPUT_Rooms!$V$4:$V$83, INPUT_Rooms!$A$4:$A$83=$B$3),4)&amp;" coat(s) on "&amp;A9&amp;" trim ("&amp;TEXTJOIN(", ",TRUE,IF(INDEX(FILTER(INPUT_Rooms!$X$4:$X$83, INPUT_Rooms!$A$4:$A$83=$B$3),4)="Y","base",""),IF(INDEX(FILTER(INPUT_Rooms!$Y$4:$Y$83, INPUT_Rooms!$A$4:$A$83=$B$3),4)="Y","crown",""),IF(INDEX(FILTER(INPUT_Rooms!$Z$4:$Z$83, INPUT_Rooms!$A$4:$A$83=$B$3),4)="Y","window casing",""),IF(INDEX(FILTER(INPUT_Rooms!$AA$4:$AA$83, INPUT_Rooms!$A$4:$A$83=$B$3),4)="Y","door casing",""),IF(INDEX(FILTER(INPUT_Rooms!$AB$4:$AB$83, INPUT_Rooms!$A$4:$A$83=$B$3),4)="Y","doors",""))&amp;").", "")))</f><v></v></c><c r="D9" s="2" t="inlineStr"><is><t>Primer:</t></is></c><c r="E9" s="3"><f>XLOOKUP('Job Control'!$B$3, INPUT_JobSettings!$A:$A, INPUT_JobSettings!$N:$N, "")</f><v></v></c></row><row r="10"><c r="A10" s="6"><f>IFERROR(INDEX(FILTER(INPUT_Rooms!$C$4:$C$83, INPUT_Rooms!$A$4:$A$83=$B$3), 5), "")</f><v></v></c><c r="B10" s="6"><f>IF(A10="","",TEXTJOIN(" ",TRUE,IF(INDEX(FILTER(INPUT_Rooms!$K$4:$K$83, INPUT_Rooms!$A$4:$A$83=$B$3),5)="Y","Prep and paint "&amp;INDEX(FILTER(INPUT_Rooms!$M$4:$M$83, INPUT_Rooms!$A$4:$A$83=$B$3),5)&amp;" coat(s) on "&amp;A10&amp;" walls.", ""),IF(INDEX(FILTER(INPUT_Rooms!$O$4:$O$83, INPUT_Rooms!$A$4:$A$83=$B$3),5)="Y","Prep and paint "&amp;INDEX(FILTER(INPUT_Rooms!$Q$4:$Q$83, INPUT_Rooms!$A$4:$A$83=$B$3),5)&amp;" coat(s) on "&amp;A10&amp;" ceilings.", ""),IF(INDEX(FILTER(INPUT_Rooms!$T$4:$T$83, INPUT_Rooms!$A$4:$A$83=$B$3),5)="Y","Prep and paint "&amp;INDEX(FILTER(INPUT_Rooms!$V$4:$V$83, INPUT_Rooms!$A$4:$A$83=$B$3),5)&amp;" coat(s) on "&amp;A10&amp;" trim ("&amp;TEXTJOIN(", ",TRUE,IF(INDEX(FILTER(INPUT_Rooms!$X$4:$X$83, INPUT_Rooms!$A$4:$A$83=$B$3),5)="Y","base",""),IF(INDEX(FILTER(INPUT_Rooms!$Y$4:$Y$83, INPUT_Rooms!$A$4:$A$83=$B$3),5)="Y","crown",""),IF(INDEX(FILTER(INPUT_Rooms!$Z$4:$Z$83, INPUT_Rooms!$A$4:$A$83=$B$3),5)="Y","window casing",""),IF(INDEX(FILTER(INPUT_Rooms!$AA$4:$AA$83, INPUT_Rooms!$A$4:$A$83=$B$3),5)="Y","door casing",""),IF(INDEX(FILTER(INPUT_Rooms!$AB$4:$AB$83, INPUT_Rooms!$A$4:$A$83=$B$3),5)="Y","doors",""))&amp;").", "")))</f><v></v></c></row><row r="11"><c r="A11" s="6"><f>IFERROR(INDEX(FILTER(INPUT_Rooms!$C$4:$C$83, INPUT_Rooms!$A$4:$A$83=$B$3), 6), "")</f><v></v></c><c r="B11" s="6"><f>IF(A11="","",TEXTJOIN(" ",TRUE,IF(INDEX(FILTER(INPUT_Rooms!$K$4:$K$83, INPUT_Rooms!$A$4:$A$83=$B$3),6)="Y","Prep and paint "&amp;INDEX(FILTER(INPUT_Rooms!$M$4:$M$83, INPUT_Rooms!$A$4:$A$83=$B$3),6)&amp;" coat(s) on "&amp;A11&amp;" walls.", ""),IF(INDEX(FILTER(INPUT_Rooms!$O$4:$O$83, INPUT_Rooms!$A$4:$A$83=$B$3),6)="Y","Prep and paint "&amp;INDEX(FILTER(INPUT_Rooms!$Q$4:$Q$83, INPUT_Rooms!$A$4:$A$83=$B$3),6)&amp;" coat(s) on "&amp;A11&amp;" ceilings.", ""),IF(INDEX(FILTER(INPUT_Rooms!$T$4:$T$83, INPUT_Rooms!$A$4:$A$83=$B$3),6)="Y","Prep and paint "&amp;INDEX(FILTER(INPUT_Rooms!$V$4:$V$83, INPUT_Rooms!$A$4:$A$83=$B$3),6)&amp;" coat(s) on "&amp;A11&amp;" trim ("&amp;TEXTJOIN(", ",TRUE,IF(INDEX(FILTER(INPUT_Rooms!$X$4:$X$83, INPUT_Rooms!$A$4:$A$83=$B$3),6)="Y","base",""),IF(INDEX(FILTER(INPUT_Rooms!$Y$4:$Y$83, INPUT_Rooms!$A$4:$A$83=$B$3),6)="Y","crown",""),IF(INDEX(FILTER(INPUT_Rooms!$Z$4:$Z$83, INPUT_Rooms!$A$4:$A$83=$B$3),6)="Y","window casing",""),IF(INDEX(FILTER(INPUT_Rooms!$AA$4:$AA$83, INPUT_Rooms!$A$4:$A$83=$B$3),6)="Y","door casing",""),IF(INDEX(FILTER(INPUT_Rooms!$AB$4:$AB$83, INPUT_Rooms!$A$4:$A$83=$B$3),6)="Y","doors",""))&amp;").", "")))</f><v></v></c></row><row r="12"><c r="A12" s="6"><f>IFERROR(INDEX(FILTER(INPUT_Rooms!$C$4:$C$83, INPUT_Rooms!$A$4:$A$83=$B$3), 7), "")</f><v></v></c><c r="B12" s="6"><f>IF(A12="","",TEXTJOIN(" ",TRUE,IF(INDEX(FILTER(INPUT_Rooms!$K$4:$K$83, INPUT_Rooms!$A$4:$A$83=$B$3),7)="Y","Prep and paint "&amp;INDEX(FILTER(INPUT_Rooms!$M$4:$M$83, INPUT_Rooms!$A$4:$A$83=$B$3),7)&amp;" coat(s) on "&amp;A12&amp;" walls.", ""),IF(INDEX(FILTER(INPUT_Rooms!$O$4:$O$83, INPUT_Rooms!$A$4:$A$83=$B$3),7)="Y","Prep and paint "&amp;INDEX(FILTER(INPUT_Rooms!$Q$4:$Q$83, INPUT_Rooms!$A$4:$A$83=$B$3),7)&amp;" coat(s) on "&amp;A12&amp;" ceilings.", ""),IF(INDEX(FILTER(INPUT_Rooms!$T$4:$T$83, INPUT_Rooms!$A$4:$A$83=$B$3),7)="Y","Prep and paint "&amp;INDEX(FILTER(INPUT_Rooms!$V$4:$V$83, INPUT_Rooms!$A$4:$A$83=$B$3),7)&amp;" coat(s) on "&amp;A12&amp;" trim ("&amp;TEXTJOIN(", ",TRUE,IF(INDEX(FILTER(INPUT_Rooms!$X$4:$X$83, INPUT_Rooms!$A$4:$A$83=$B$3),7)="Y","base",""),IF(INDEX(FILTER(INPUT_Rooms!$Y$4:$Y$83, INPUT_Rooms!$A$4:$A$83=$B$3),7)="Y","crown",""),IF(INDEX(FILTER(INPUT_Rooms!$Z$4:$Z$83, INPUT_Rooms!$A$4:$A$83=$B$3),7)="Y","window casing",""),IF(INDEX(FILTER(INPUT_Rooms!$AA$4:$AA$83, INPUT_Rooms!$A$4:$A$83=$B$3),7)="Y","door casing",""),IF(INDEX(FILTER(INPUT_Rooms!$AB$4:$AB$83, INPUT_Rooms!$A$4:$A$83=$B$3),7)="Y","doors",""))&amp;").", "")))</f><v></v></c></row><row r="13"><c r="A13" s="6"><f>IFERROR(INDEX(FILTER(INPUT_Rooms!$C$4:$C$83, INPUT_Rooms!$A$4:$A$83=$B$3), 8), "")</f><v></v></c><c r="B13" s="6"><f>IF(A13="","",TEXTJOIN(" ",TRUE,IF(INDEX(FILTER(INPUT_Rooms!$K$4:$K$83, INPUT_Rooms!$A$4:$A$83=$B$3),8)="Y","Prep and paint "&amp;INDEX(FILTER(INPUT_Rooms!$M$4:$M$83, INPUT_Rooms!$A$4:$A$83=$B$3),8)&amp;" coat(s) on "&amp;A13&amp;" walls.", ""),IF(INDEX(FILTER(INPUT_Rooms!$O$4:$O$83, INPUT_Rooms!$A$4:$A$83=$B$3),8)="Y","Prep and paint "&amp;INDEX(FILTER(INPUT_Rooms!$Q$4:$Q$83, INPUT_Rooms!$A$4:$A$83=$B$3),8)&amp;" coat(s) on "&amp;A13&amp;" ceilings.", ""),IF(INDEX(FILTER(INPUT_Rooms!$T$4:$T$83, INPUT_Rooms!$A$4:$A$83=$B$3),8)="Y","Prep and paint "&amp;INDEX(FILTER(INPUT_Rooms!$V$4:$V$83, INPUT_Rooms!$A$4:$A$83=$B$3),8)&amp;" coat(s) on "&amp;A13&amp;" trim ("&amp;TEXTJOIN(", ",TRUE,IF(INDEX(FILTER(INPUT_Rooms!$X$4:$X$83, INPUT_Rooms!$A$4:$A$83=$B$3),8)="Y","base",""),IF(INDEX(FILTER(INPUT_Rooms!$Y$4:$Y$83, INPUT_Rooms!$A$4:$A$83=$B$3),8)="Y","crown",""),IF(INDEX(FILTER(INPUT_Rooms!$Z$4:$Z$83, INPUT_Rooms!$A$4:$A$83=$B$3),8)="Y","window casing",""),IF(INDEX(FILTER(INPUT_Rooms!$AA$4:$AA$83, INPUT_Rooms!$A$4:$A$83=$B$3),8)="Y","door casing",""),IF(INDEX(FILTER(INPUT_Rooms!$AB$4:$AB$83, INPUT_Rooms!$A$4:$A$83=$B$3),8)="Y","doors",""))&amp;").", "")))</f><v></v></c></row><row r="14"><c r="A14" s="6"><f>IFERROR(INDEX(FILTER(INPUT_Rooms!$C$4:$C$83, INPUT_Rooms!$A$4:$A$83=$B$3), 9), "")</f><v></v></c><c r="B14" s="6"><f>IF(A14="","",TEXTJOIN(" ",TRUE,IF(INDEX(FILTER(INPUT_Rooms!$K$4:$K$83, INPUT_Rooms!$A$4:$A$83=$B$3),9)="Y","Prep and paint "&amp;INDEX(FILTER(INPUT_Rooms!$M$4:$M$83, INPUT_Rooms!$A$4:$A$83=$B$3),9)&amp;" coat(s) on "&amp;A14&amp;" walls.", ""),IF(INDEX(FILTER(INPUT_Rooms!$O$4:$O$83, INPUT_Rooms!$A$4:$A$83=$B$3),9)="Y","Prep and paint "&amp;INDEX(FILTER(INPUT_Rooms!$Q$4:$Q$83, INPUT_Rooms!$A$4:$A$83=$B$3),9)&amp;" coat(s) on "&amp;A14&amp;" ceilings.", ""),IF(INDEX(FILTER(INPUT_Rooms!$T$4:$T$83, INPUT_Rooms!$A$4:$A$83=$B$3),9)="Y","Prep and paint "&amp;INDEX(FILTER(INPUT_Rooms!$V$4:$V$83, INPUT_Rooms!$A$4:$A$83=$B$3),9)&amp;" coat(s) on "&amp;A14&amp;" trim ("&amp;TEXTJOIN(", ",TRUE,IF(INDEX(FILTER(INPUT_Rooms!$X$4:$X$83, INPUT_Rooms!$A$4:$A$83=$B$3),9)="Y","base",""),IF(INDEX(FILTER(INPUT_Rooms!$Y$4:$Y$83, INPUT_Rooms!$A$4:$A$83=$B$3),9)="Y","crown",""),IF(INDEX(FILTER(INPUT_Rooms!$Z$4:$Z$83, INPUT_Rooms!$A$4:$A$83=$B$3),9)="Y","window casing",""),IF(INDEX(FILTER(INPUT_Rooms!$AA$4:$AA$83, INPUT_Rooms!$A$4:$A$83=$B$3),9)="Y","door casing",""),IF(INDEX(FILTER(INPUT_Rooms!$AB$4:$AB$83, INPUT_Rooms!$A$4:$A$83=$B$3),9)="Y","doors",""))&amp;").", "")))</f><v></v></c></row><row r="15"><c r="A15" s="6"><f>IFERROR(INDEX(FILTER(INPUT_Rooms!$C$4:$C$83, INPUT_Rooms!$A$4:$A$83=$B$3), 10), "")</f><v></v></c><c r="B15" s="6"><f>IF(A15="","",TEXTJOIN(" ",TRUE,IF(INDEX(FILTER(INPUT_Rooms!$K$4:$K$83, INPUT_Rooms!$A$4:$A$83=$B$3),10)="Y","Prep and paint "&amp;INDEX(FILTER(INPUT_Rooms!$M$4:$M$83, INPUT_Rooms!$A$4:$A$83=$B$3),10)&amp;" coat(s) on "&amp;A15&amp;" walls.", ""),IF(INDEX(FILTER(INPUT_Rooms!$O$4:$O$83, INPUT_Rooms!$A$4:$A$83=$B$3),10)="Y","Prep and paint "&amp;INDEX(FILTER(INPUT_Rooms!$Q$4:$Q$83, INPUT_Rooms!$A$4:$A$83=$B$3),10)&amp;" coat(s) on "&amp;A15&amp;" ceilings.", ""),IF(INDEX(FILTER(INPUT_Rooms!$T$4:$T$83, INPUT_Rooms!$A$4:$A$83=$B$3),10)="Y","Prep and paint "&amp;INDEX(FILTER(INPUT_Rooms!$V$4:$V$83, INPUT_Rooms!$A$4:$A$83=$B$3),10)&amp;" coat(s) on "&amp;A15&amp;" trim ("&amp;TEXTJOIN(", ",TRUE,IF(INDEX(FILTER(INPUT_Rooms!$X$4:$X$83, INPUT_Rooms!$A$4:$A$83=$B$3),10)="Y","base",""),IF(INDEX(FILTER(INPUT_Rooms!$Y$4:$Y$83, INPUT_Rooms!$A$4:$A$83=$B$3),10)="Y","crown",""),IF(INDEX(FILTER(INPUT_Rooms!$Z$4:$Z$83, INPUT_Rooms!$A$4:$A$83=$B$3),10)="Y","window casing",""),IF(INDEX(FILTER(INPUT_Rooms!$AA$4:$AA$83, INPUT_Rooms!$A$4:$A$83=$B$3),10)="Y","door casing",""),IF(INDEX(FILTER(INPUT_Rooms!$AB$4:$AB$83, INPUT_Rooms!$A$4:$A$83=$B$3),10)="Y","doors",""))&amp;").", "")))</f><v></v></c></row><row r="16"><c r="A16" s="6"><f>IFERROR(INDEX(FILTER(INPUT_Rooms!$C$4:$C$83, INPUT_Rooms!$A$4:$A$83=$B$3), 11), "")</f><v></v></c><c r="B16" s="6"><f>IF(A16="","",TEXTJOIN(" ",TRUE,IF(INDEX(FILTER(INPUT_Rooms!$K$4:$K$83, INPUT_Rooms!$A$4:$A$83=$B$3),11)="Y","Prep and paint "&amp;INDEX(FILTER(INPUT_Rooms!$M$4:$M$83, INPUT_Rooms!$A$4:$A$83=$B$3),11)&amp;" coat(s) on "&amp;A16&amp;" walls.", ""),IF(INDEX(FILTER(INPUT_Rooms!$O$4:$O$83, INPUT_Rooms!$A$4:$A$83=$B$3),11)="Y","Prep and paint "&amp;INDEX(FILTER(INPUT_Rooms!$Q$4:$Q$83, INPUT_Rooms!$A$4:$A$83=$B$3),11)&amp;" coat(s) on "&amp;A16&amp;" ceilings.", ""),IF(INDEX(FILTER(INPUT_Rooms!$T$4:$T$83, INPUT_Rooms!$A$4:$A$83=$B$3),11)="Y","Prep and paint "&amp;INDEX(FILTER(INPUT_Rooms!$V$4:$V$83, INPUT_Rooms!$A$4:$A$83=$B$3),11)&amp;" coat(s) on "&amp;A16&amp;" trim ("&amp;TEXTJOIN(", ",TRUE,IF(INDEX(FILTER(INPUT_Rooms!$X$4:$X$83, INPUT_Rooms!$A$4:$A$83=$B$3),11)="Y","base",""),IF(INDEX(FILTER(INPUT_Rooms!$Y$4:$Y$83, INPUT_Rooms!$A$4:$A$83=$B$3),11)="Y","crown",""),IF(INDEX(FILTER(INPUT_Rooms!$Z$4:$Z$83, INPUT_Rooms!$A$4:$A$83=$B$3),11)="Y","window casing",""),IF(INDEX(FILTER(INPUT_Rooms!$AA$4:$AA$83, INPUT_Rooms!$A$4:$A$83=$B$3),11)="Y","door casing",""),IF(INDEX(FILTER(INPUT_Rooms!$AB$4:$AB$83, INPUT_Rooms!$A$4:$A$83=$B$3),11)="Y","doors",""))&amp;").", "")))</f><v></v></c></row><row r="17"><c r="A17" s="6"><f>IFERROR(INDEX(FILTER(INPUT_Rooms!$C$4:$C$83, INPUT_Rooms!$A$4:$A$83=$B$3), 12), "")</f><v></v></c><c r="B17" s="6"><f>IF(A17="","",TEXTJOIN(" ",TRUE,IF(INDEX(FILTER(INPUT_Rooms!$K$4:$K$83, INPUT_Rooms!$A$4:$A$83=$B$3),12)="Y","Prep and paint "&amp;INDEX(FILTER(INPUT_Rooms!$M$4:$M$83, INPUT_Rooms!$A$4:$A$83=$B$3),12)&amp;" coat(s) on "&amp;A17&amp;" walls.", ""),IF(INDEX(FILTER(INPUT_Rooms!$O$4:$O$83, INPUT_Rooms!$A$4:$A$83=$B$3),12)="Y","Prep and paint "&amp;INDEX(FILTER(INPUT_Rooms!$Q$4:$Q$83, INPUT_Rooms!$A$4:$A$83=$B$3),12)&amp;" coat(s) on "&amp;A17&amp;" ceilings.", ""),IF(INDEX(FILTER(INPUT_Rooms!$T$4:$T$83, INPUT_Rooms!$A$4:$A$83=$B$3),12)="Y","Prep and paint "&amp;INDEX(FILTER(INPUT_Rooms!$V$4:$V$83, INPUT_Rooms!$A$4:$A$83=$B$3),12)&amp;" coat(s) on "&amp;A17&amp;" trim ("&amp;TEXTJOIN(", ",TRUE,IF(INDEX(FILTER(INPUT_Rooms!$X$4:$X$83, INPUT_Rooms!$A$4:$A$83=$B$3),12)="Y","base",""),IF(INDEX(FILTER(INPUT_Rooms!$Y$4:$Y$83, INPUT_Rooms!$A$4:$A$83=$B$3),12)="Y","crown",""),IF(INDEX(FILTER(INPUT_Rooms!$Z$4:$Z$83, INPUT_Rooms!$A$4:$A$83=$B$3),12)="Y","window casing",""),IF(INDEX(FILTER(INPUT_Rooms!$AA$4:$AA$83, INPUT_Rooms!$A$4:$A$83=$B$3),12)="Y","door casing",""),IF(INDEX(FILTER(INPUT_Rooms!$AB$4:$AB$83, INPUT_Rooms!$A$4:$A$83=$B$3),12)="Y","doors",""))&amp;").", "")))</f><v></v></c></row><row r="18"><c r="A18" s="6"><f>IFERROR(INDEX(FILTER(INPUT_Rooms!$C$4:$C$83, INPUT_Rooms!$A$4:$A$83=$B$3), 13), "")</f><v></v></c><c r="B18" s="6"><f>IF(A18="","",TEXTJOIN(" ",TRUE,IF(INDEX(FILTER(INPUT_Rooms!$K$4:$K$83, INPUT_Rooms!$A$4:$A$83=$B$3),13)="Y","Prep and paint "&amp;INDEX(FILTER(INPUT_Rooms!$M$4:$M$83, INPUT_Rooms!$A$4:$A$83=$B$3),13)&amp;" coat(s) on "&amp;A18&amp;" walls.", ""),IF(INDEX(FILTER(INPUT_Rooms!$O$4:$O$83, INPUT_Rooms!$A$4:$A$83=$B$3),13)="Y","Prep and paint "&amp;INDEX(FILTER(INPUT_Rooms!$Q$4:$Q$83, INPUT_Rooms!$A$4:$A$83=$B$3),13)&amp;" coat(s) on "&amp;A18&amp;" ceilings.", ""),IF(INDEX(FILTER(INPUT_Rooms!$T$4:$T$83, INPUT_Rooms!$A$4:$A$83=$B$3),13)="Y","Prep and paint "&amp;INDEX(FILTER(INPUT_Rooms!$V$4:$V$83, INPUT_Rooms!$A$4:$A$83=$B$3),13)&amp;" coat(s) on "&amp;A18&amp;" trim ("&amp;TEXTJOIN(", ",TRUE,IF(INDEX(FILTER(INPUT_Rooms!$X$4:$X$83, INPUT_Rooms!$A$4:$A$83=$B$3),13)="Y","base",""),IF(INDEX(FILTER(INPUT_Rooms!$Y$4:$Y$83, INPUT_Rooms!$A$4:$A$83=$B$3),13)="Y","crown",""),IF(INDEX(FILTER(INPUT_Rooms!$Z$4:$Z$83, INPUT_Rooms!$A$4:$A$83=$B$3),13)="Y","window casing",""),IF(INDEX(FILTER(INPUT_Rooms!$AA$4:$AA$83, INPUT_Rooms!$A$4:$A$83=$B$3),13)="Y","door casing",""),IF(INDEX(FILTER(INPUT_Rooms!$AB$4:$AB$83, INPUT_Rooms!$A$4:$A$83=$B$3),13)="Y","doors",""))&amp;").", "")))</f><v></v></c></row><row r="19"><c r="A19" s="6"><f>IFERROR(INDEX(FILTER(INPUT_Rooms!$C$4:$C$83, INPUT_Rooms!$A$4:$A$83=$B$3), 14), "")</f><v></v></c><c r="B19" s="6"><f>IF(A19="","",TEXTJOIN(" ",TRUE,IF(INDEX(FILTER(INPUT_Rooms!$K$4:$K$83, INPUT_Rooms!$A$4:$A$83=$B$3),14)="Y","Prep and paint "&amp;INDEX(FILTER(INPUT_Rooms!$M$4:$M$83, INPUT_Rooms!$A$4:$A$83=$B$3),14)&amp;" coat(s) on "&amp;A19&amp;" walls.", ""),IF(INDEX(FILTER(INPUT_Rooms!$O$4:$O$83, INPUT_Rooms!$A$4:$A$83=$B$3),14)="Y","Prep and paint "&amp;INDEX(FILTER(INPUT_Rooms!$Q$4:$Q$83, INPUT_Rooms!$A$4:$A$83=$B$3),14)&amp;" coat(s) on "&amp;A19&amp;" ceilings.", ""),IF(INDEX(FILTER(INPUT_Rooms!$T$4:$T$83, INPUT_Rooms!$A$4:$A$83=$B$3),14)="Y","Prep and paint "&amp;INDEX(FILTER(INPUT_Rooms!$V$4:$V$83, INPUT_Rooms!$A$4:$A$83=$B$3),14)&amp;" coat(s) on "&amp;A19&amp;" trim ("&amp;TEXTJOIN(", ",TRUE,IF(INDEX(FILTER(INPUT_Rooms!$X$4:$X$83, INPUT_Rooms!$A$4:$A$83=$B$3),14)="Y","base",""),IF(INDEX(FILTER(INPUT_Rooms!$Y$4:$Y$83, INPUT_Rooms!$A$4:$A$83=$B$3),14)="Y","crown",""),IF(INDEX(FILTER(INPUT_Rooms!$Z$4:$Z$83, INPUT_Rooms!$A$4:$A$83=$B$3),14)="Y","window casing",""),IF(INDEX(FILTER(INPUT_Rooms!$AA$4:$AA$83, INPUT_Rooms!$A$4:$A$83=$B$3),14)="Y","door casing",""),IF(INDEX(FILTER(INPUT_Rooms!$AB$4:$AB$83, INPUT_Rooms!$A$4:$A$83=$B$3),14)="Y","doors",""))&amp;").", "")))</f><v></v></c></row><row r="20"><c r="A20" s="6"><f>IFERROR(INDEX(FILTER(INPUT_Rooms!$C$4:$C$83, INPUT_Rooms!$A$4:$A$83=$B$3), 15), "")</f><v></v></c><c r="B20" s="6"><f>IF(A20="","",TEXTJOIN(" ",TRUE,IF(INDEX(FILTER(INPUT_Rooms!$K$4:$K$83, INPUT_Rooms!$A$4:$A$83=$B$3),15)="Y","Prep and paint "&amp;INDEX(FILTER(INPUT_Rooms!$M$4:$M$83, INPUT_Rooms!$A$4:$A$83=$B$3),15)&amp;" coat(s) on "&amp;A20&amp;" walls.", ""),IF(INDEX(FILTER(INPUT_Rooms!$O$4:$O$83, INPUT_Rooms!$A$4:$A$83=$B$3),15)="Y","Prep and paint "&amp;INDEX(FILTER(INPUT_Rooms!$Q$4:$Q$83, INPUT_Rooms!$A$4:$A$83=$B$3),15)&amp;" coat(s) on "&amp;A20&amp;" ceilings.", ""),IF(INDEX(FILTER(INPUT_Rooms!$T$4:$T$83, INPUT_Rooms!$A$4:$A$83=$B$3),15)="Y","Prep and paint "&amp;INDEX(FILTER(INPUT_Rooms!$V$4:$V$83, INPUT_Rooms!$A$4:$A$83=$B$3),15)&amp;" coat(s) on "&amp;A20&amp;" trim ("&amp;TEXTJOIN(", ",TRUE,IF(INDEX(FILTER(INPUT_Rooms!$X$4:$X$83, INPUT_Rooms!$A$4:$A$83=$B$3),15)="Y","base",""),IF(INDEX(FILTER(INPUT_Rooms!$Y$4:$Y$83, INPUT_Rooms!$A$4:$A$83=$B$3),15)="Y","crown",""),IF(INDEX(FILTER(INPUT_Rooms!$Z$4:$Z$83, INPUT_Rooms!$A$4:$A$83=$B$3),15)="Y","window casing",""),IF(INDEX(FILTER(INPUT_Rooms!$AA$4:$AA$83, INPUT_Rooms!$A$4:$A$83=$B$3),15)="Y","door casing",""),IF(INDEX(FILTER(INPUT_Rooms!$AB$4:$AB$83, INPUT_Rooms!$A$4:$A$83=$B$3),15)="Y","doors",""))&amp;").", "")))</f><v></v></c></row><row r="21"><c r="A21" s="6"><f>IFERROR(INDEX(FILTER(INPUT_Rooms!$C$4:$C$83, INPUT_Rooms!$A$4:$A$83=$B$3), 16), "")</f><v></v></c><c r="B21" s="6"><f>IF(A21="","",TEXTJOIN(" ",TRUE,IF(INDEX(FILTER(INPUT_Rooms!$K$4:$K$83, INPUT_Rooms!$A$4:$A$83=$B$3),16)="Y","Prep and paint "&amp;INDEX(FILTER(INPUT_Rooms!$M$4:$M$83, INPUT_Rooms!$A$4:$A$83=$B$3),16)&amp;" coat(s) on "&amp;A21&amp;" walls.", ""),IF(INDEX(FILTER(INPUT_Rooms!$O$4:$O$83, INPUT_Rooms!$A$4:$A$83=$B$3),16)="Y","Prep and paint "&amp;INDEX(FILTER(INPUT_Rooms!$Q$4:$Q$83, INPUT_Rooms!$A$4:$A$83=$B$3),16)&amp;" coat(s) on "&amp;A21&amp;" ceilings.", ""),IF(INDEX(FILTER(INPUT_Rooms!$T$4:$T$83, INPUT_Rooms!$A$4:$A$83=$B$3),16)="Y","Prep and paint "&amp;INDEX(FILTER(INPUT_Rooms!$V$4:$V$83, INPUT_Rooms!$A$4:$A$83=$B$3),16)&amp;" coat(s) on "&amp;A21&amp;" trim ("&amp;TEXTJOIN(", ",TRUE,IF(INDEX(FILTER(INPUT_Rooms!$X$4:$X$83, INPUT_Rooms!$A$4:$A$83=$B$3),16)="Y","base",""),IF(INDEX(FILTER(INPUT_Rooms!$Y$4:$Y$83, INPUT_Rooms!$A$4:$A$83=$B$3),16)="Y","crown",""),IF(INDEX(FILTER(INPUT_Rooms!$Z$4:$Z$83, INPUT_Rooms!$A$4:$A$83=$B$3),16)="Y","window casing",""),IF(INDEX(FILTER(INPUT_Rooms!$AA$4:$AA$83, INPUT_Rooms!$A$4:$A$83=$B$3),16)="Y","door casing",""),IF(INDEX(FILTER(INPUT_Rooms!$AB$4:$AB$83, INPUT_Rooms!$A$4:$A$83=$B$3),16)="Y","doors",""))&amp;").", "")))</f><v></v></c></row><row r="22"><c r="A22" s="6"><f>IFERROR(INDEX(FILTER(INPUT_Rooms!$C$4:$C$83, INPUT_Rooms!$A$4:$A$83=$B$3), 17), "")</f><v></v></c><c r="B22" s="6"><f>IF(A22="","",TEXTJOIN(" ",TRUE,IF(INDEX(FILTER(INPUT_Rooms!$K$4:$K$83, INPUT_Rooms!$A$4:$A$83=$B$3),17)="Y","Prep and paint "&amp;INDEX(FILTER(INPUT_Rooms!$M$4:$M$83, INPUT_Rooms!$A$4:$A$83=$B$3),17)&amp;" coat(s) on "&amp;A22&amp;" walls.", ""),IF(INDEX(FILTER(INPUT_Rooms!$O$4:$O$83, INPUT_Rooms!$A$4:$A$83=$B$3),17)="Y","Prep and paint "&amp;INDEX(FILTER(INPUT_Rooms!$Q$4:$Q$83, INPUT_Rooms!$A$4:$A$83=$B$3),17)&amp;" coat(s) on "&amp;A22&amp;" ceilings.", ""),IF(INDEX(FILTER(INPUT_Rooms!$T$4:$T$83, INPUT_Rooms!$A$4:$A$83=$B$3),17)="Y","Prep and paint "&amp;INDEX(FILTER(INPUT_Rooms!$V$4:$V$83, INPUT_Rooms!$A$4:$A$83=$B$3),17)&amp;" coat(s) on "&amp;A22&amp;" trim ("&amp;TEXTJOIN(", ",TRUE,IF(INDEX(FILTER(INPUT_Rooms!$X$4:$X$83, INPUT_Rooms!$A$4:$A$83=$B$3),17)="Y","base",""),IF(INDEX(FILTER(INPUT_Rooms!$Y$4:$Y$83, INPUT_Rooms!$A$4:$A$83=$B$3),17)="Y","crown",""),IF(INDEX(FILTER(INPUT_Rooms!$Z$4:$Z$83, INPUT_Rooms!$A$4:$A$83=$B$3),17)="Y","window casing",""),IF(INDEX(FILTER(INPUT_Rooms!$AA$4:$AA$83, INPUT_Rooms!$A$4:$A$83=$B$3),17)="Y","door casing",""),IF(INDEX(FILTER(INPUT_Rooms!$AB$4:$AB$83, INPUT_Rooms!$A$4:$A$83=$B$3),17)="Y","doors",""))&amp;").", "")))</f><v></v></c></row><row r="23"><c r="A23" s="6"><f>IFERROR(INDEX(FILTER(INPUT_Rooms!$C$4:$C$83, INPUT_Rooms!$A$4:$A$83=$B$3), 18), "")</f><v></v></c><c r="B23" s="6"><f>IF(A23="","",TEXTJOIN(" ",TRUE,IF(INDEX(FILTER(INPUT_Rooms!$K$4:$K$83, INPUT_Rooms!$A$4:$A$83=$B$3),18)="Y","Prep and paint "&amp;INDEX(FILTER(INPUT_Rooms!$M$4:$M$83, INPUT_Rooms!$A$4:$A$83=$B$3),18)&amp;" coat(s) on "&amp;A23&amp;" walls.", ""),IF(INDEX(FILTER(INPUT_Rooms!$O$4:$O$83, INPUT_Rooms!$A$4:$A$83=$B$3),18)="Y","Prep and paint "&amp;INDEX(FILTER(INPUT_Rooms!$Q$4:$Q$83, INPUT_Rooms!$A$4:$A$83=$B$3),18)&amp;" coat(s) on "&amp;A23&amp;" ceilings.", ""),IF(INDEX(FILTER(INPUT_Rooms!$T$4:$T$83, INPUT_Rooms!$A$4:$A$83=$B$3),18)="Y","Prep and paint "&amp;INDEX(FILTER(INPUT_Rooms!$V$4:$V$83, INPUT_Rooms!$A$4:$A$83=$B$3),18)&amp;" coat(s) on "&amp;A23&amp;" trim ("&amp;TEXTJOIN(", ",TRUE,IF(INDEX(FILTER(INPUT_Rooms!$X$4:$X$83, INPUT_Rooms!$A$4:$A$83=$B$3),18)="Y","base",""),IF(INDEX(FILTER(INPUT_Rooms!$Y$4:$Y$83, INPUT_Rooms!$A$4:$A$83=$B$3),18)="Y","crown",""),IF(INDEX(FILTER(INPUT_Rooms!$Z$4:$Z$83, INPUT_Rooms!$A$4:$A$83=$B$3),18)="Y","window casing",""),IF(INDEX(FILTER(INPUT_Rooms!$AA$4:$AA$83, INPUT_Rooms!$A$4:$A$83=$B$3),18)="Y","door casing",""),IF(INDEX(FILTER(INPUT_Rooms!$AB$4:$AB$83, INPUT_Rooms!$A$4:$A$83=$B$3),18)="Y","doors",""))&amp;").", "")))</f><v></v></c></row><row r="24"><c r="A24" s="6"><f>IFERROR(INDEX(FILTER(INPUT_Rooms!$C$4:$C$83, INPUT_Rooms!$A$4:$A$83=$B$3), 19), "")</f><v></v></c><c r="B24" s="6"><f>IF(A24="","",TEXTJOIN(" ",TRUE,IF(INDEX(FILTER(INPUT_Rooms!$K$4:$K$83, INPUT_Rooms!$A$4:$A$83=$B$3),19)="Y","Prep and paint "&amp;INDEX(FILTER(INPUT_Rooms!$M$4:$M$83, INPUT_Rooms!$A$4:$A$83=$B$3),19)&amp;" coat(s) on "&amp;A24&amp;" walls.", ""),IF(INDEX(FILTER(INPUT_Rooms!$O$4:$O$83, INPUT_Rooms!$A$4:$A$83=$B$3),19)="Y","Prep and paint "&amp;INDEX(FILTER(INPUT_Rooms!$Q$4:$Q$83, INPUT_Rooms!$A$4:$A$83=$B$3),19)&amp;" coat(s) on "&amp;A24&amp;" ceilings.", ""),IF(INDEX(FILTER(INPUT_Rooms!$T$4:$T$83, INPUT_Rooms!$A$4:$A$83=$B$3),19)="Y","Prep and paint "&amp;INDEX(FILTER(INPUT_Rooms!$V$4:$V$83, INPUT_Rooms!$A$4:$A$83=$B$3),19)&amp;" coat(s) on "&amp;A24&amp;" trim ("&amp;TEXTJOIN(", ",TRUE,IF(INDEX(FILTER(INPUT_Rooms!$X$4:$X$83, INPUT_Rooms!$A$4:$A$83=$B$3),19)="Y","base",""),IF(INDEX(FILTER(INPUT_Rooms!$Y$4:$Y$83, INPUT_Rooms!$A$4:$A$83=$B$3),19)="Y","crown",""),IF(INDEX(FILTER(INPUT_Rooms!$Z$4:$Z$83, INPUT_Rooms!$A$4:$A$83=$B$3),19)="Y","window casing",""),IF(INDEX(FILTER(INPUT_Rooms!$AA$4:$AA$83, INPUT_Rooms!$A$4:$A$83=$B$3),19)="Y","door casing",""),IF(INDEX(FILTER(INPUT_Rooms!$AB$4:$AB$83, INPUT_Rooms!$A$4:$A$83=$B$3),19)="Y","doors",""))&amp;").", "")))</f><v></v></c></row><row r="25"><c r="A25" s="6"><f>IFERROR(INDEX(FILTER(INPUT_Rooms!$C$4:$C$83, INPUT_Rooms!$A$4:$A$83=$B$3), 20), "")</f><v></v></c><c r="B25" s="6"><f>IF(A25="","",TEXTJOIN(" ",TRUE,IF(INDEX(FILTER(INPUT_Rooms!$K$4:$K$83, INPUT_Rooms!$A$4:$A$83=$B$3),20)="Y","Prep and paint "&amp;INDEX(FILTER(INPUT_Rooms!$M$4:$M$83, INPUT_Rooms!$A$4:$A$83=$B$3),20)&amp;" coat(s) on "&amp;A25&amp;" walls.", ""),IF(INDEX(FILTER(INPUT_Rooms!$O$4:$O$83, INPUT_Rooms!$A$4:$A$83=$B$3),20)="Y","Prep and paint "&amp;INDEX(FILTER(INPUT_Rooms!$Q$4:$Q$83, INPUT_Rooms!$A$4:$A$83=$B$3),20)&amp;" coat(s) on "&amp;A25&amp;" ceilings.", ""),IF(INDEX(FILTER(INPUT_Rooms!$T$4:$T$83, INPUT_Rooms!$A$4:$A$83=$B$3),20)="Y","Prep and paint "&amp;INDEX(FILTER(INPUT_Rooms!$V$4:$V$83, INPUT_Rooms!$A$4:$A$83=$B$3),20)&amp;" coat(s) on "&amp;A25&amp;" trim ("&amp;TEXTJOIN(", ",TRUE,IF(INDEX(FILTER(INPUT_Rooms!$X$4:$X$83, INPUT_Rooms!$A$4:$A$83=$B$3),20)="Y","base",""),IF(INDEX(FILTER(INPUT_Rooms!$Y$4:$Y$83, INPUT_Rooms!$A$4:$A$83=$B$3),20)="Y","crown",""),IF(INDEX(FILTER(INPUT_Rooms!$Z$4:$Z$83, INPUT_Rooms!$A$4:$A$83=$B$3),20)="Y","window casing",""),IF(INDEX(FILTER(INPUT_Rooms!$AA$4:$AA$83, INPUT_Rooms!$A$4:$A$83=$B$3),20)="Y","door casing",""),IF(INDEX(FILTER(INPUT_Rooms!$AB$4:$AB$83, INPUT_Rooms!$A$4:$A$83=$B$3),20)="Y","doors",""))&amp;").", "")))</f><v></v></c></row><row r="26"><c r="A26" s="6"><f>IFERROR(INDEX(FILTER(INPUT_Rooms!$C$4:$C$83, INPUT_Rooms!$A$4:$A$83=$B$3), 21), "")</f><v></v></c><c r="B26" s="6"><f>IF(A26="","",TEXTJOIN(" ",TRUE,IF(INDEX(FILTER(INPUT_Rooms!$K$4:$K$83, INPUT_Rooms!$A$4:$A$83=$B$3),21)="Y","Prep and paint "&amp;INDEX(FILTER(INPUT_Rooms!$M$4:$M$83, INPUT_Rooms!$A$4:$A$83=$B$3),21)&amp;" coat(s) on "&amp;A26&amp;" walls.", ""),IF(INDEX(FILTER(INPUT_Rooms!$O$4:$O$83, INPUT_Rooms!$A$4:$A$83=$B$3),21)="Y","Prep and paint "&amp;INDEX(FILTER(INPUT_Rooms!$Q$4:$Q$83, INPUT_Rooms!$A$4:$A$83=$B$3),21)&amp;" coat(s) on "&amp;A26&amp;" ceilings.", ""),IF(INDEX(FILTER(INPUT_Rooms!$T$4:$T$83, INPUT_Rooms!$A$4:$A$83=$B$3),21)="Y","Prep and paint "&amp;INDEX(FILTER(INPUT_Rooms!$V$4:$V$83, INPUT_Rooms!$A$4:$A$83=$B$3),21)&amp;" coat(s) on "&amp;A26&amp;" trim ("&amp;TEXTJOIN(", ",TRUE,IF(INDEX(FILTER(INPUT_Rooms!$X$4:$X$83, INPUT_Rooms!$A$4:$A$83=$B$3),21)="Y","base",""),IF(INDEX(FILTER(INPUT_Rooms!$Y$4:$Y$83, INPUT_Rooms!$A$4:$A$83=$B$3),21)="Y","crown",""),IF(INDEX(FILTER(INPUT_Rooms!$Z$4:$Z$83, INPUT_Rooms!$A$4:$A$83=$B$3),21)="Y","window casing",""),IF(INDEX(FILTER(INPUT_Rooms!$AA$4:$AA$83, INPUT_Rooms!$A$4:$A$83=$B$3),21)="Y","door casing",""),IF(INDEX(FILTER(INPUT_Rooms!$AB$4:$AB$83, INPUT_Rooms!$A$4:$A$83=$B$3),21)="Y","doors",""))&amp;").", "")))</f><v></v></c></row><row r="27"><c r="A27" s="6"><f>IFERROR(INDEX(FILTER(INPUT_Rooms!$C$4:$C$83, INPUT_Rooms!$A$4:$A$83=$B$3), 22), "")</f><v></v></c><c r="B27" s="6"><f>IF(A27="","",TEXTJOIN(" ",TRUE,IF(INDEX(FILTER(INPUT_Rooms!$K$4:$K$83, INPUT_Rooms!$A$4:$A$83=$B$3),22)="Y","Prep and paint "&amp;INDEX(FILTER(INPUT_Rooms!$M$4:$M$83, INPUT_Rooms!$A$4:$A$83=$B$3),22)&amp;" coat(s) on "&amp;A27&amp;" walls.", ""),IF(INDEX(FILTER(INPUT_Rooms!$O$4:$O$83, INPUT_Rooms!$A$4:$A$83=$B$3),22)="Y","Prep and paint "&amp;INDEX(FILTER(INPUT_Rooms!$Q$4:$Q$83, INPUT_Rooms!$A$4:$A$83=$B$3),22)&amp;" coat(s) on "&amp;A27&amp;" ceilings.", ""),IF(INDEX(FILTER(INPUT_Rooms!$T$4:$T$83, INPUT_Rooms!$A$4:$A$83=$B$3),22)="Y","Prep and paint "&amp;INDEX(FILTER(INPUT_Rooms!$V$4:$V$83, INPUT_Rooms!$A$4:$A$83=$B$3),22)&amp;" coat(s) on "&amp;A27&amp;" trim ("&amp;TEXTJOIN(", ",TRUE,IF(INDEX(FILTER(INPUT_Rooms!$X$4:$X$83, INPUT_Rooms!$A$4:$A$83=$B$3),22)="Y","base",""),IF(INDEX(FILTER(INPUT_Rooms!$Y$4:$Y$83, INPUT_Rooms!$A$4:$A$83=$B$3),22)="Y","crown",""),IF(INDEX(FILTER(INPUT_Rooms!$Z$4:$Z$83, INPUT_Rooms!$A$4:$A$83=$B$3),22)="Y","window casing",""),IF(INDEX(FILTER(INPUT_Rooms!$AA$4:$AA$83, INPUT_Rooms!$A$4:$A$83=$B$3),22)="Y","door casing",""),IF(INDEX(FILTER(INPUT_Rooms!$AB$4:$AB$83, INPUT_Rooms!$A$4:$A$83=$B$3),22)="Y","doors",""))&amp;").", "")))</f><v></v></c></row><row r="28"><c r="A28" s="6"><f>IFERROR(INDEX(FILTER(INPUT_Rooms!$C$4:$C$83, INPUT_Rooms!$A$4:$A$83=$B$3), 23), "")</f><v></v></c><c r="B28" s="6"><f>IF(A28="","",TEXTJOIN(" ",TRUE,IF(INDEX(FILTER(INPUT_Rooms!$K$4:$K$83, INPUT_Rooms!$A$4:$A$83=$B$3),23)="Y","Prep and paint "&amp;INDEX(FILTER(INPUT_Rooms!$M$4:$M$83, INPUT_Rooms!$A$4:$A$83=$B$3),23)&amp;" coat(s) on "&amp;A28&amp;" walls.", ""),IF(INDEX(FILTER(INPUT_Rooms!$O$4:$O$83, INPUT_Rooms!$A$4:$A$83=$B$3),23)="Y","Prep and paint "&amp;INDEX(FILTER(INPUT_Rooms!$Q$4:$Q$83, INPUT_Rooms!$A$4:$A$83=$B$3),23)&amp;" coat(s) on "&amp;A28&amp;" ceilings.", ""),IF(INDEX(FILTER(INPUT_Rooms!$T$4:$T$83, INPUT_Rooms!$A$4:$A$83=$B$3),23)="Y","Prep and paint "&amp;INDEX(FILTER(INPUT_Rooms!$V$4:$V$83, INPUT_Rooms!$A$4:$A$83=$B$3),23)&amp;" coat(s) on "&amp;A28&amp;" trim ("&amp;TEXTJOIN(", ",TRUE,IF(INDEX(FILTER(INPUT_Rooms!$X$4:$X$83, INPUT_Rooms!$A$4:$A$83=$B$3),23)="Y","base",""),IF(INDEX(FILTER(INPUT_Rooms!$Y$4:$Y$83, INPUT_Rooms!$A$4:$A$83=$B$3),23)="Y","crown",""),IF(INDEX(FILTER(INPUT_Rooms!$Z$4:$Z$83, INPUT_Rooms!$A$4:$A$83=$B$3),23)="Y","window casing",""),IF(INDEX(FILTER(INPUT_Rooms!$AA$4:$AA$83, INPUT_Rooms!$A$4:$A$83=$B$3),23)="Y","door casing",""),IF(INDEX(FILTER(INPUT_Rooms!$AB$4:$AB$83, INPUT_Rooms!$A$4:$A$83=$B$3),23)="Y","doors",""))&amp;").", "")))</f><v></v></c></row><row r="29"><c r="A29" s="6"><f>IFERROR(INDEX(FILTER(INPUT_Rooms!$C$4:$C$83, INPUT_Rooms!$A$4:$A$83=$B$3), 24), "")</f><v></v></c><c r="B29" s="6"><f>IF(A29="","",TEXTJOIN(" ",TRUE,IF(INDEX(FILTER(INPUT_Rooms!$K$4:$K$83, INPUT_Rooms!$A$4:$A$83=$B$3),24)="Y","Prep and paint "&amp;INDEX(FILTER(INPUT_Rooms!$M$4:$M$83, INPUT_Rooms!$A$4:$A$83=$B$3),24)&amp;" coat(s) on "&amp;A29&amp;" walls.", ""),IF(INDEX(FILTER(INPUT_Rooms!$O$4:$O$83, INPUT_Rooms!$A$4:$A$83=$B$3),24)="Y","Prep and paint "&amp;INDEX(FILTER(INPUT_Rooms!$Q$4:$Q$83, INPUT_Rooms!$A$4:$A$83=$B$3),24)&amp;" coat(s) on "&amp;A29&amp;" ceilings.", ""),IF(INDEX(FILTER(INPUT_Rooms!$T$4:$T$83, INPUT_Rooms!$A$4:$A$83=$B$3),24)="Y","Prep and paint "&amp;INDEX(FILTER(INPUT_Rooms!$V$4:$V$83, INPUT_Rooms!$A$4:$A$83=$B$3),24)&amp;" coat(s) on "&amp;A29&amp;" trim ("&amp;TEXTJOIN(", ",TRUE,IF(INDEX(FILTER(INPUT_Rooms!$X$4:$X$83, INPUT_Rooms!$A$4:$A$83=$B$3),24)="Y","base",""),IF(INDEX(FILTER(INPUT_Rooms!$Y$4:$Y$83, INPUT_Rooms!$A$4:$A$83=$B$3),24)="Y","crown",""),IF(INDEX(FILTER(INPUT_Rooms!$Z$4:$Z$83, INPUT_Rooms!$A$4:$A$83=$B$3),24)="Y","window casing",""),IF(INDEX(FILTER(INPUT_Rooms!$AA$4:$AA$83, INPUT_Rooms!$A$4:$A$83=$B$3),24)="Y","door casing",""),IF(INDEX(FILTER(INPUT_Rooms!$AB$4:$AB$83, INPUT_Rooms!$A$4:$A$83=$B$3),24)="Y","doors",""))&amp;").", "")))</f><v></v></c></row><row r="30"><c r="A30" s="6"><f>IFERROR(INDEX(FILTER(INPUT_Rooms!$C$4:$C$83, INPUT_Rooms!$A$4:$A$83=$B$3), 25), "")</f><v></v></c><c r="B30" s="6"><f>IF(A30="","",TEXTJOIN(" ",TRUE,IF(INDEX(FILTER(INPUT_Rooms!$K$4:$K$83, INPUT_Rooms!$A$4:$A$83=$B$3),25)="Y","Prep and paint "&amp;INDEX(FILTER(INPUT_Rooms!$M$4:$M$83, INPUT_Rooms!$A$4:$A$83=$B$3),25)&amp;" coat(s) on "&amp;A30&amp;" walls.", ""),IF(INDEX(FILTER(INPUT_Rooms!$O$4:$O$83, INPUT_Rooms!$A$4:$A$83=$B$3),25)="Y","Prep and paint "&amp;INDEX(FILTER(INPUT_Rooms!$Q$4:$Q$83, INPUT_Rooms!$A$4:$A$83=$B$3),25)&amp;" coat(s) on "&amp;A30&amp;" ceilings.", ""),IF(INDEX(FILTER(INPUT_Rooms!$T$4:$T$83, INPUT_Rooms!$A$4:$A$83=$B$3),25)="Y","Prep and paint "&amp;INDEX(FILTER(INPUT_Rooms!$V$4:$V$83, INPUT_Rooms!$A$4:$A$83=$B$3),25)&amp;" coat(s) on "&amp;A30&amp;" trim ("&amp;TEXTJOIN(", ",TRUE,IF(INDEX(FILTER(INPUT_Rooms!$X$4:$X$83, INPUT_Rooms!$A$4:$A$83=$B$3),25)="Y","base",""),IF(INDEX(FILTER(INPUT_Rooms!$Y$4:$Y$83, INPUT_Rooms!$A$4:$A$83=$B$3),25)="Y","crown",""),IF(INDEX(FILTER(INPUT_Rooms!$Z$4:$Z$83, INPUT_Rooms!$A$4:$A$83=$B$3),25)="Y","window casing",""),IF(INDEX(FILTER(INPUT_Rooms!$AA$4:$AA$83, INPUT_Rooms!$A$4:$A$83=$B$3),25)="Y","door casing",""),IF(INDEX(FILTER(INPUT_Rooms!$AB$4:$AB$83, INPUT_Rooms!$A$4:$A$83=$B$3),25)="Y","doors",""))&amp;").", "")))</f><v></v></c></row><row r="31"><c r="A31" s="6"><f>IFERROR(INDEX(FILTER(INPUT_Rooms!$C$4:$C$83, INPUT_Rooms!$A$4:$A$83=$B$3), 26), "")</f><v></v></c><c r="B31" s="6"><f>IF(A31="","",TEXTJOIN(" ",TRUE,IF(INDEX(FILTER(INPUT_Rooms!$K$4:$K$83, INPUT_Rooms!$A$4:$A$83=$B$3),26)="Y","Prep and paint "&amp;INDEX(FILTER(INPUT_Rooms!$M$4:$M$83, INPUT_Rooms!$A$4:$A$83=$B$3),26)&amp;" coat(s) on "&amp;A31&amp;" walls.", ""),IF(INDEX(FILTER(INPUT_Rooms!$O$4:$O$83, INPUT_Rooms!$A$4:$A$83=$B$3),26)="Y","Prep and paint "&amp;INDEX(FILTER(INPUT_Rooms!$Q$4:$Q$83, INPUT_Rooms!$A$4:$A$83=$B$3),26)&amp;" coat(s) on "&amp;A31&amp;" ceilings.", ""),IF(INDEX(FILTER(INPUT_Rooms!$T$4:$T$83, INPUT_Rooms!$A$4:$A$83=$B$3),26)="Y","Prep and paint "&amp;INDEX(FILTER(INPUT_Rooms!$V$4:$V$83, INPUT_Rooms!$A$4:$A$83=$B$3),26)&amp;" coat(s) on "&amp;A31&amp;" trim ("&amp;TEXTJOIN(", ",TRUE,IF(INDEX(FILTER(INPUT_Rooms!$X$4:$X$83, INPUT_Rooms!$A$4:$A$83=$B$3),26)="Y","base",""),IF(INDEX(FILTER(INPUT_Rooms!$Y$4:$Y$83, INPUT_Rooms!$A$4:$A$83=$B$3),26)="Y","crown",""),IF(INDEX(FILTER(INPUT_Rooms!$Z$4:$Z$83, INPUT_Rooms!$A$4:$A$83=$B$3),26)="Y","window casing",""),IF(INDEX(FILTER(INPUT_Rooms!$AA$4:$AA$83, INPUT_Rooms!$A$4:$A$83=$B$3),26)="Y","door casing",""),IF(INDEX(FILTER(INPUT_Rooms!$AB$4:$AB$83, INPUT_Rooms!$A$4:$A$83=$B$3),26)="Y","doors",""))&amp;").", "")))</f><v></v></c></row><row r="32"><c r="A32" s="6"><f>IFERROR(INDEX(FILTER(INPUT_Rooms!$C$4:$C$83, INPUT_Rooms!$A$4:$A$83=$B$3), 27), "")</f><v></v></c><c r="B32" s="6"><f>IF(A32="","",TEXTJOIN(" ",TRUE,IF(INDEX(FILTER(INPUT_Rooms!$K$4:$K$83, INPUT_Rooms!$A$4:$A$83=$B$3),27)="Y","Prep and paint "&amp;INDEX(FILTER(INPUT_Rooms!$M$4:$M$83, INPUT_Rooms!$A$4:$A$83=$B$3),27)&amp;" coat(s) on "&amp;A32&amp;" walls.", ""),IF(INDEX(FILTER(INPUT_Rooms!$O$4:$O$83, INPUT_Rooms!$A$4:$A$83=$B$3),27)="Y","Prep and paint "&amp;INDEX(FILTER(INPUT_Rooms!$Q$4:$Q$83, INPUT_Rooms!$A$4:$A$83=$B$3),27)&amp;" coat(s) on "&amp;A32&amp;" ceilings.", ""),IF(INDEX(FILTER(INPUT_Rooms!$T$4:$T$83, INPUT_Rooms!$A$4:$A$83=$B$3),27)="Y","Prep and paint "&amp;INDEX(FILTER(INPUT_Rooms!$V$4:$V$83, INPUT_Rooms!$A$4:$A$83=$B$3),27)&amp;" coat(s) on "&amp;A32&amp;" trim ("&amp;TEXTJOIN(", ",TRUE,IF(INDEX(FILTER(INPUT_Rooms!$X$4:$X$83, INPUT_Rooms!$A$4:$A$83=$B$3),27)="Y","base",""),IF(INDEX(FILTER(INPUT_Rooms!$Y$4:$Y$83, INPUT_Rooms!$A$4:$A$83=$B$3),27)="Y","crown",""),IF(INDEX(FILTER(INPUT_Rooms!$Z$4:$Z$83, INPUT_Rooms!$A$4:$A$83=$B$3),27)="Y","window casing",""),IF(INDEX(FILTER(INPUT_Rooms!$AA$4:$AA$83, INPUT_Rooms!$A$4:$A$83=$B$3),27)="Y","door casing",""),IF(INDEX(FILTER(INPUT_Rooms!$AB$4:$AB$83, INPUT_Rooms!$A$4:$A$83=$B$3),27)="Y","doors",""))&amp;").", "")))</f><v></v></c></row><row r="33"><c r="A33" s="6"><f>IFERROR(INDEX(FILTER(INPUT_Rooms!$C$4:$C$83, INPUT_Rooms!$A$4:$A$83=$B$3), 28), "")</f><v></v></c><c r="B33" s="6"><f>IF(A33="","",TEXTJOIN(" ",TRUE,IF(INDEX(FILTER(INPUT_Rooms!$K$4:$K$83, INPUT_Rooms!$A$4:$A$83=$B$3),28)="Y","Prep and paint "&amp;INDEX(FILTER(INPUT_Rooms!$M$4:$M$83, INPUT_Rooms!$A$4:$A$83=$B$3),28)&amp;" coat(s) on "&amp;A33&amp;" walls.", ""),IF(INDEX(FILTER(INPUT_Rooms!$O$4:$O$83, INPUT_Rooms!$A$4:$A$83=$B$3),28)="Y","Prep and paint "&amp;INDEX(FILTER(INPUT_Rooms!$Q$4:$Q$83, INPUT_Rooms!$A$4:$A$83=$B$3),28)&amp;" coat(s) on "&amp;A33&amp;" ceilings.", ""),IF(INDEX(FILTER(INPUT_Rooms!$T$4:$T$83, INPUT_Rooms!$A$4:$A$83=$B$3),28)="Y","Prep and paint "&amp;INDEX(FILTER(INPUT_Rooms!$V$4:$V$83, INPUT_Rooms!$A$4:$A$83=$B$3),28)&amp;" coat(s) on "&amp;A33&amp;" trim ("&amp;TEXTJOIN(", ",TRUE,IF(INDEX(FILTER(INPUT_Rooms!$X$4:$X$83, INPUT_Rooms!$A$4:$A$83=$B$3),28)="Y","base",""),IF(INDEX(FILTER(INPUT_Rooms!$Y$4:$Y$83, INPUT_Rooms!$A$4:$A$83=$B$3),28)="Y","crown",""),IF(INDEX(FILTER(INPUT_Rooms!$Z$4:$Z$83, INPUT_Rooms!$A$4:$A$83=$B$3),28)="Y","window casing",""),IF(INDEX(FILTER(INPUT_Rooms!$AA$4:$AA$83, INPUT_Rooms!$A$4:$A$83=$B$3),28)="Y","door casing",""),IF(INDEX(FILTER(INPUT_Rooms!$AB$4:$AB$83, INPUT_Rooms!$A$4:$A$83=$B$3),28)="Y","doors",""))&amp;").", "")))</f><v></v></c></row><row r="34"><c r="A34" s="6"><f>IFERROR(INDEX(FILTER(INPUT_Rooms!$C$4:$C$83, INPUT_Rooms!$A$4:$A$83=$B$3), 29), "")</f><v></v></c><c r="B34" s="6"><f>IF(A34="","",TEXTJOIN(" ",TRUE,IF(INDEX(FILTER(INPUT_Rooms!$K$4:$K$83, INPUT_Rooms!$A$4:$A$83=$B$3),29)="Y","Prep and paint "&amp;INDEX(FILTER(INPUT_Rooms!$M$4:$M$83, INPUT_Rooms!$A$4:$A$83=$B$3),29)&amp;" coat(s) on "&amp;A34&amp;" walls.", ""),IF(INDEX(FILTER(INPUT_Rooms!$O$4:$O$83, INPUT_Rooms!$A$4:$A$83=$B$3),29)="Y","Prep and paint "&amp;INDEX(FILTER(INPUT_Rooms!$Q$4:$Q$83, INPUT_Rooms!$A$4:$A$83=$B$3),29)&amp;" coat(s) on "&amp;A34&amp;" ceilings.", ""),IF(INDEX(FILTER(INPUT_Rooms!$T$4:$T$83, INPUT_Rooms!$A$4:$A$83=$B$3),29)="Y","Prep and paint "&amp;INDEX(FILTER(INPUT_Rooms!$V$4:$V$83, INPUT_Rooms!$A$4:$A$83=$B$3),29)&amp;" coat(s) on "&amp;A34&amp;" trim ("&amp;TEXTJOIN(", ",TRUE,IF(INDEX(FILTER(INPUT_Rooms!$X$4:$X$83, INPUT_Rooms!$A$4:$A$83=$B$3),29)="Y","base",""),IF(INDEX(FILTER(INPUT_Rooms!$Y$4:$Y$83, INPUT_Rooms!$A$4:$A$83=$B$3),29)="Y","crown",""),IF(INDEX(FILTER(INPUT_Rooms!$Z$4:$Z$83, INPUT_Rooms!$A$4:$A$83=$B$3),29)="Y","window casing",""),IF(INDEX(FILTER(INPUT_Rooms!$AA$4:$AA$83, INPUT_Rooms!$A$4:$A$83=$B$3),29)="Y","door casing",""),IF(INDEX(FILTER(INPUT_Rooms!$AB$4:$AB$83, INPUT_Rooms!$A$4:$A$83=$B$3),29)="Y","doors",""))&amp;").", "")))</f><v></v></c></row><row r="35"><c r="A35" s="6"><f>IFERROR(INDEX(FILTER(INPUT_Rooms!$C$4:$C$83, INPUT_Rooms!$A$4:$A$83=$B$3), 30), "")</f><v></v></c><c r="B35" s="6"><f>IF(A35="","",TEXTJOIN(" ",TRUE,IF(INDEX(FILTER(INPUT_Rooms!$K$4:$K$83, INPUT_Rooms!$A$4:$A$83=$B$3),30)="Y","Prep and paint "&amp;INDEX(FILTER(INPUT_Rooms!$M$4:$M$83, INPUT_Rooms!$A$4:$A$83=$B$3),30)&amp;" coat(s) on "&amp;A35&amp;" walls.", ""),IF(INDEX(FILTER(INPUT_Rooms!$O$4:$O$83, INPUT_Rooms!$A$4:$A$83=$B$3),30)="Y","Prep and paint "&amp;INDEX(FILTER(INPUT_Rooms!$Q$4:$Q$83, INPUT_Rooms!$A$4:$A$83=$B$3),30)&amp;" coat(s) on "&amp;A35&amp;" ceilings.", ""),IF(INDEX(FILTER(INPUT_Rooms!$T$4:$T$83, INPUT_Rooms!$A$4:$A$83=$B$3),30)="Y","Prep and paint "&amp;INDEX(FILTER(INPUT_Rooms!$V$4:$V$83, INPUT_Rooms!$A$4:$A$83=$B$3),30)&amp;" coat(s) on "&amp;A35&amp;" trim ("&amp;TEXTJOIN(", ",TRUE,IF(INDEX(FILTER(INPUT_Rooms!$X$4:$X$83, INPUT_Rooms!$A$4:$A$83=$B$3),30)="Y","base",""),IF(INDEX(FILTER(INPUT_Rooms!$Y$4:$Y$83, INPUT_Rooms!$A$4:$A$83=$B$3),30)="Y","crown",""),IF(INDEX(FILTER(INPUT_Rooms!$Z$4:$Z$83, INPUT_Rooms!$A$4:$A$83=$B$3),30)="Y","window casing",""),IF(INDEX(FILTER(INPUT_Rooms!$AA$4:$AA$83, INPUT_Rooms!$A$4:$A$83=$B$3),30)="Y","door casing",""),IF(INDEX(FILTER(INPUT_Rooms!$AB$4:$AB$83, INPUT_Rooms!$A$4:$A$83=$B$3),30)="Y","doors",""))&amp;").", "")))</f><v></v></c></row><row r="36"><c r="A36" s="6"><f>IFERROR(INDEX(FILTER(INPUT_Rooms!$C$4:$C$83, INPUT_Rooms!$A$4:$A$83=$B$3), 31), "")</f><v></v></c><c r="B36" s="6"><f>IF(A36="","",TEXTJOIN(" ",TRUE,IF(INDEX(FILTER(INPUT_Rooms!$K$4:$K$83, INPUT_Rooms!$A$4:$A$83=$B$3),31)="Y","Prep and paint "&amp;INDEX(FILTER(INPUT_Rooms!$M$4:$M$83, INPUT_Rooms!$A$4:$A$83=$B$3),31)&amp;" coat(s) on "&amp;A36&amp;" walls.", ""),IF(INDEX(FILTER(INPUT_Rooms!$O$4:$O$83, INPUT_Rooms!$A$4:$A$83=$B$3),31)="Y","Prep and paint "&amp;INDEX(FILTER(INPUT_Rooms!$Q$4:$Q$83, INPUT_Rooms!$A$4:$A$83=$B$3),31)&amp;" coat(s) on "&amp;A36&amp;" ceilings.", ""),IF(INDEX(FILTER(INPUT_Rooms!$T$4:$T$83, INPUT_Rooms!$A$4:$A$83=$B$3),31)="Y","Prep and paint "&amp;INDEX(FILTER(INPUT_Rooms!$V$4:$V$83, INPUT_Rooms!$A$4:$A$83=$B$3),31)&amp;" coat(s) on "&amp;A36&amp;" trim ("&amp;TEXTJOIN(", ",TRUE,IF(INDEX(FILTER(INPUT_Rooms!$X$4:$X$83, INPUT_Rooms!$A$4:$A$83=$B$3),31)="Y","base",""),IF(INDEX(FILTER(INPUT_Rooms!$Y$4:$Y$83, INPUT_Rooms!$A$4:$A$83=$B$3),31)="Y","crown",""),IF(INDEX(FILTER(INPUT_Rooms!$Z$4:$Z$83, INPUT_Rooms!$A$4:$A$83=$B$3),31)="Y","window casing",""),IF(INDEX(FILTER(INPUT_Rooms!$AA$4:$AA$83, INPUT_Rooms!$A$4:$A$83=$B$3),31)="Y","door casing",""),IF(INDEX(FILTER(INPUT_Rooms!$AB$4:$AB$83, INPUT_Rooms!$A$4:$A$83=$B$3),31)="Y","doors",""))&amp;").", "")))</f><v></v></c></row><row r="37"><c r="A37" s="6"><f>IFERROR(INDEX(FILTER(INPUT_Rooms!$C$4:$C$83, INPUT_Rooms!$A$4:$A$83=$B$3), 32), "")</f><v></v></c><c r="B37" s="6"><f>IF(A37="","",TEXTJOIN(" ",TRUE,IF(INDEX(FILTER(INPUT_Rooms!$K$4:$K$83, INPUT_Rooms!$A$4:$A$83=$B$3),32)="Y","Prep and paint "&amp;INDEX(FILTER(INPUT_Rooms!$M$4:$M$83, INPUT_Rooms!$A$4:$A$83=$B$3),32)&amp;" coat(s) on "&amp;A37&amp;" walls.", ""),IF(INDEX(FILTER(INPUT_Rooms!$O$4:$O$83, INPUT_Rooms!$A$4:$A$83=$B$3),32)="Y","Prep and paint "&amp;INDEX(FILTER(INPUT_Rooms!$Q$4:$Q$83, INPUT_Rooms!$A$4:$A$83=$B$3),32)&amp;" coat(s) on "&amp;A37&amp;" ceilings.", ""),IF(INDEX(FILTER(INPUT_Rooms!$T$4:$T$83, INPUT_Rooms!$A$4:$A$83=$B$3),32)="Y","Prep and paint "&amp;INDEX(FILTER(INPUT_Rooms!$V$4:$V$83, INPUT_Rooms!$A$4:$A$83=$B$3),32)&amp;" coat(s) on "&amp;A37&amp;" trim ("&amp;TEXTJOIN(", ",TRUE,IF(INDEX(FILTER(INPUT_Rooms!$X$4:$X$83, INPUT_Rooms!$A$4:$A$83=$B$3),32)="Y","base",""),IF(INDEX(FILTER(INPUT_Rooms!$Y$4:$Y$83, INPUT_Rooms!$A$4:$A$83=$B$3),32)="Y","crown",""),IF(INDEX(FILTER(INPUT_Rooms!$Z$4:$Z$83, INPUT_Rooms!$A$4:$A$83=$B$3),32)="Y","window casing",""),IF(INDEX(FILTER(INPUT_Rooms!$AA$4:$AA$83, INPUT_Rooms!$A$4:$A$83=$B$3),32)="Y","door casing",""),IF(INDEX(FILTER(INPUT_Rooms!$AB$4:$AB$83, INPUT_Rooms!$A$4:$A$83=$B$3),32)="Y","doors",""))&amp;").", "")))</f><v></v></c></row><row r="38"><c r="A38" s="6"><f>IFERROR(INDEX(FILTER(INPUT_Rooms!$C$4:$C$83, INPUT_Rooms!$A$4:$A$83=$B$3), 33), "")</f><v></v></c><c r="B38" s="6"><f>IF(A38="","",TEXTJOIN(" ",TRUE,IF(INDEX(FILTER(INPUT_Rooms!$K$4:$K$83, INPUT_Rooms!$A$4:$A$83=$B$3),33)="Y","Prep and paint "&amp;INDEX(FILTER(INPUT_Rooms!$M$4:$M$83, INPUT_Rooms!$A$4:$A$83=$B$3),33)&amp;" coat(s) on "&amp;A38&amp;" walls.", ""),IF(INDEX(FILTER(INPUT_Rooms!$O$4:$O$83, INPUT_Rooms!$A$4:$A$83=$B$3),33)="Y","Prep and paint "&amp;INDEX(FILTER(INPUT_Rooms!$Q$4:$Q$83, INPUT_Rooms!$A$4:$A$83=$B$3),33)&amp;" coat(s) on "&amp;A38&amp;" ceilings.", ""),IF(INDEX(FILTER(INPUT_Rooms!$T$4:$T$83, INPUT_Rooms!$A$4:$A$83=$B$3),33)="Y","Prep and paint "&amp;INDEX(FILTER(INPUT_Rooms!$V$4:$V$83, INPUT_Rooms!$A$4:$A$83=$B$3),33)&amp;" coat(s) on "&amp;A38&amp;" trim ("&amp;TEXTJOIN(", ",TRUE,IF(INDEX(FILTER(INPUT_Rooms!$X$4:$X$83, INPUT_Rooms!$A$4:$A$83=$B$3),33)="Y","base",""),IF(INDEX(FILTER(INPUT_Rooms!$Y$4:$Y$83, INPUT_Rooms!$A$4:$A$83=$B$3),33)="Y","crown",""),IF(INDEX(FILTER(INPUT_Rooms!$Z$4:$Z$83, INPUT_Rooms!$A$4:$A$83=$B$3),33)="Y","window casing",""),IF(INDEX(FILTER(INPUT_Rooms!$AA$4:$AA$83, INPUT_Rooms!$A$4:$A$83=$B$3),33)="Y","door casing",""),IF(INDEX(FILTER(INPUT_Rooms!$AB$4:$AB$83, INPUT_Rooms!$A$4:$A$83=$B$3),33)="Y","doors",""))&amp;").", "")))</f><v></v></c></row><row r="39"><c r="A39" s="6"><f>IFERROR(INDEX(FILTER(INPUT_Rooms!$C$4:$C$83, INPUT_Rooms!$A$4:$A$83=$B$3), 34), "")</f><v></v></c><c r="B39" s="6"><f>IF(A39="","",TEXTJOIN(" ",TRUE,IF(INDEX(FILTER(INPUT_Rooms!$K$4:$K$83, INPUT_Rooms!$A$4:$A$83=$B$3),34)="Y","Prep and paint "&amp;INDEX(FILTER(INPUT_Rooms!$M$4:$M$83, INPUT_Rooms!$A$4:$A$83=$B$3),34)&amp;" coat(s) on "&amp;A39&amp;" walls.", ""),IF(INDEX(FILTER(INPUT_Rooms!$O$4:$O$83, INPUT_Rooms!$A$4:$A$83=$B$3),34)="Y","Prep and paint "&amp;INDEX(FILTER(INPUT_Rooms!$Q$4:$Q$83, INPUT_Rooms!$A$4:$A$83=$B$3),34)&amp;" coat(s) on "&amp;A39&amp;" ceilings.", ""),IF(INDEX(FILTER(INPUT_Rooms!$T$4:$T$83, INPUT_Rooms!$A$4:$A$83=$B$3),34)="Y","Prep and paint "&amp;INDEX(FILTER(INPUT_Rooms!$V$4:$V$83, INPUT_Rooms!$A$4:$A$83=$B$3),34)&amp;" coat(s) on "&amp;A39&amp;" trim ("&amp;TEXTJOIN(", ",TRUE,IF(INDEX(FILTER(INPUT_Rooms!$X$4:$X$83, INPUT_Rooms!$A$4:$A$83=$B$3),34)="Y","base",""),IF(INDEX(FILTER(INPUT_Rooms!$Y$4:$Y$83, INPUT_Rooms!$A$4:$A$83=$B$3),34)="Y","crown",""),IF(INDEX(FILTER(INPUT_Rooms!$Z$4:$Z$83, INPUT_Rooms!$A$4:$A$83=$B$3),34)="Y","window casing",""),IF(INDEX(FILTER(INPUT_Rooms!$AA$4:$AA$83, INPUT_Rooms!$A$4:$A$83=$B$3),34)="Y","door casing",""),IF(INDEX(FILTER(INPUT_Rooms!$AB$4:$AB$83, INPUT_Rooms!$A$4:$A$83=$B$3),34)="Y","doors",""))&amp;").", "")))</f><v></v></c></row><row r="40"><c r="A40" s="6"><f>IFERROR(INDEX(FILTER(INPUT_Rooms!$C$4:$C$83, INPUT_Rooms!$A$4:$A$83=$B$3), 35), "")</f><v></v></c><c r="B40" s="6"><f>IF(A40="","",TEXTJOIN(" ",TRUE,IF(INDEX(FILTER(INPUT_Rooms!$K$4:$K$83, INPUT_Rooms!$A$4:$A$83=$B$3),35)="Y","Prep and paint "&amp;INDEX(FILTER(INPUT_Rooms!$M$4:$M$83, INPUT_Rooms!$A$4:$A$83=$B$3),35)&amp;" coat(s) on "&amp;A40&amp;" walls.", ""),IF(INDEX(FILTER(INPUT_Rooms!$O$4:$O$83, INPUT_Rooms!$A$4:$A$83=$B$3),35)="Y","Prep and paint "&amp;INDEX(FILTER(INPUT_Rooms!$Q$4:$Q$83, INPUT_Rooms!$A$4:$A$83=$B$3),35)&amp;" coat(s) on "&amp;A40&amp;" ceilings.", ""),IF(INDEX(FILTER(INPUT_Rooms!$T$4:$T$83, INPUT_Rooms!$A$4:$A$83=$B$3),35)="Y","Prep and paint "&amp;INDEX(FILTER(INPUT_Rooms!$V$4:$V$83, INPUT_Rooms!$A$4:$A$83=$B$3),35)&amp;" coat(s) on "&amp;A40&amp;" trim ("&amp;TEXTJOIN(", ",TRUE,IF(INDEX(FILTER(INPUT_Rooms!$X$4:$X$83, INPUT_Rooms!$A$4:$A$83=$B$3),35)="Y","base",""),IF(INDEX(FILTER(INPUT_Rooms!$Y$4:$Y$83, INPUT_Rooms!$A$4:$A$83=$B$3),35)="Y","crown",""),IF(INDEX(FILTER(INPUT_Rooms!$Z$4:$Z$83, INPUT_Rooms!$A$4:$A$83=$B$3),35)="Y","window casing",""),IF(INDEX(FILTER(INPUT_Rooms!$AA$4:$AA$83, INPUT_Rooms!$A$4:$A$83=$B$3),35)="Y","door casing",""),IF(INDEX(FILTER(INPUT_Rooms!$AB$4:$AB$83, INPUT_Rooms!$A$4:$A$83=$B$3),35)="Y","doors",""))&amp;").", "")))</f><v></v></c></row><row r="41"><c r="A41" s="6"><f>IFERROR(INDEX(FILTER(INPUT_Rooms!$C$4:$C$83, INPUT_Rooms!$A$4:$A$83=$B$3), 36), "")</f><v></v></c><c r="B41" s="6"><f>IF(A41="","",TEXTJOIN(" ",TRUE,IF(INDEX(FILTER(INPUT_Rooms!$K$4:$K$83, INPUT_Rooms!$A$4:$A$83=$B$3),36)="Y","Prep and paint "&amp;INDEX(FILTER(INPUT_Rooms!$M$4:$M$83, INPUT_Rooms!$A$4:$A$83=$B$3),36)&amp;" coat(s) on "&amp;A41&amp;" walls.", ""),IF(INDEX(FILTER(INPUT_Rooms!$O$4:$O$83, INPUT_Rooms!$A$4:$A$83=$B$3),36)="Y","Prep and paint "&amp;INDEX(FILTER(INPUT_Rooms!$Q$4:$Q$83, INPUT_Rooms!$A$4:$A$83=$B$3),36)&amp;" coat(s) on "&amp;A41&amp;" ceilings.", ""),IF(INDEX(FILTER(INPUT_Rooms!$T$4:$T$83, INPUT_Rooms!$A$4:$A$83=$B$3),36)="Y","Prep and paint "&amp;INDEX(FILTER(INPUT_Rooms!$V$4:$V$83, INPUT_Rooms!$A$4:$A$83=$B$3),36)&amp;" coat(s) on "&amp;A41&amp;" trim ("&amp;TEXTJOIN(", ",TRUE,IF(INDEX(FILTER(INPUT_Rooms!$X$4:$X$83, INPUT_Rooms!$A$4:$A$83=$B$3),36)="Y","base",""),IF(INDEX(FILTER(INPUT_Rooms!$Y$4:$Y$83, INPUT_Rooms!$A$4:$A$83=$B$3),36)="Y","crown",""),IF(INDEX(FILTER(INPUT_Rooms!$Z$4:$Z$83, INPUT_Rooms!$A$4:$A$83=$B$3),36)="Y","window casing",""),IF(INDEX(FILTER(INPUT_Rooms!$AA$4:$AA$83, INPUT_Rooms!$A$4:$A$83=$B$3),36)="Y","door casing",""),IF(INDEX(FILTER(INPUT_Rooms!$AB$4:$AB$83, INPUT_Rooms!$A$4:$A$83=$B$3),36)="Y","doors",""))&amp;").", "")))</f><v></v></c></row><row r="42"><c r="A42" s="6"><f>IFERROR(INDEX(FILTER(INPUT_Rooms!$C$4:$C$83, INPUT_Rooms!$A$4:$A$83=$B$3), 37), "")</f><v></v></c><c r="B42" s="6"><f>IF(A42="","",TEXTJOIN(" ",TRUE,IF(INDEX(FILTER(INPUT_Rooms!$K$4:$K$83, INPUT_Rooms!$A$4:$A$83=$B$3),37)="Y","Prep and paint "&amp;INDEX(FILTER(INPUT_Rooms!$M$4:$M$83, INPUT_Rooms!$A$4:$A$83=$B$3),37)&amp;" coat(s) on "&amp;A42&amp;" walls.", ""),IF(INDEX(FILTER(INPUT_Rooms!$O$4:$O$83, INPUT_Rooms!$A$4:$A$83=$B$3),37)="Y","Prep and paint "&amp;INDEX(FILTER(INPUT_Rooms!$Q$4:$Q$83, INPUT_Rooms!$A$4:$A$83=$B$3),37)&amp;" coat(s) on "&amp;A42&amp;" ceilings.", ""),IF(INDEX(FILTER(INPUT_Rooms!$T$4:$T$83, INPUT_Rooms!$A$4:$A$83=$B$3),37)="Y","Prep and paint "&amp;INDEX(FILTER(INPUT_Rooms!$V$4:$V$83, INPUT_Rooms!$A$4:$A$83=$B$3),37)&amp;" coat(s) on "&amp;A42&amp;" trim ("&amp;TEXTJOIN(", ",TRUE,IF(INDEX(FILTER(INPUT_Rooms!$X$4:$X$83, INPUT_Rooms!$A$4:$A$83=$B$3),37)="Y","base",""),IF(INDEX(FILTER(INPUT_Rooms!$Y$4:$Y$83, INPUT_Rooms!$A$4:$A$83=$B$3),37)="Y","crown",""),IF(INDEX(FILTER(INPUT_Rooms!$Z$4:$Z$83, INPUT_Rooms!$A$4:$A$83=$B$3),37)="Y","window casing",""),IF(INDEX(FILTER(INPUT_Rooms!$AA$4:$AA$83, INPUT_Rooms!$A$4:$A$83=$B$3),37)="Y","door casing",""),IF(INDEX(FILTER(INPUT_Rooms!$AB$4:$AB$83, INPUT_Rooms!$A$4:$A$83=$B$3),37)="Y","doors",""))&amp;").", "")))</f><v></v></c></row><row r="43"><c r="A43" s="6"><f>IFERROR(INDEX(FILTER(INPUT_Rooms!$C$4:$C$83, INPUT_Rooms!$A$4:$A$83=$B$3), 38), "")</f><v></v></c><c r="B43" s="6"><f>IF(A43="","",TEXTJOIN(" ",TRUE,IF(INDEX(FILTER(INPUT_Rooms!$K$4:$K$83, INPUT_Rooms!$A$4:$A$83=$B$3),38)="Y","Prep and paint "&amp;INDEX(FILTER(INPUT_Rooms!$M$4:$M$83, INPUT_Rooms!$A$4:$A$83=$B$3),38)&amp;" coat(s) on "&amp;A43&amp;" walls.", ""),IF(INDEX(FILTER(INPUT_Rooms!$O$4:$O$83, INPUT_Rooms!$A$4:$A$83=$B$3),38)="Y","Prep and paint "&amp;INDEX(FILTER(INPUT_Rooms!$Q$4:$Q$83, INPUT_Rooms!$A$4:$A$83=$B$3),38)&amp;" coat(s) on "&amp;A43&amp;" ceilings.", ""),IF(INDEX(FILTER(INPUT_Rooms!$T$4:$T$83, INPUT_Rooms!$A$4:$A$83=$B$3),38)="Y","Prep and paint "&amp;INDEX(FILTER(INPUT_Rooms!$V$4:$V$83, INPUT_Rooms!$A$4:$A$83=$B$3),38)&amp;" coat(s) on "&amp;A43&amp;" trim ("&amp;TEXTJOIN(", ",TRUE,IF(INDEX(FILTER(INPUT_Rooms!$X$4:$X$83, INPUT_Rooms!$A$4:$A$83=$B$3),38)="Y","base",""),IF(INDEX(FILTER(INPUT_Rooms!$Y$4:$Y$83, INPUT_Rooms!$A$4:$A$83=$B$3),38)="Y","crown",""),IF(INDEX(FILTER(INPUT_Rooms!$Z$4:$Z$83, INPUT_Rooms!$A$4:$A$83=$B$3),38)="Y","window casing",""),IF(INDEX(FILTER(INPUT_Rooms!$AA$4:$AA$83, INPUT_Rooms!$A$4:$A$83=$B$3),38)="Y","door casing",""),IF(INDEX(FILTER(INPUT_Rooms!$AB$4:$AB$83, INPUT_Rooms!$A$4:$A$83=$B$3),38)="Y","doors",""))&amp;").", "")))</f><v></v></c></row><row r="44"><c r="A44" s="6"><f>IFERROR(INDEX(FILTER(INPUT_Rooms!$C$4:$C$83, INPUT_Rooms!$A$4:$A$83=$B$3), 39), "")</f><v></v></c><c r="B44" s="6"><f>IF(A44="","",TEXTJOIN(" ",TRUE,IF(INDEX(FILTER(INPUT_Rooms!$K$4:$K$83, INPUT_Rooms!$A$4:$A$83=$B$3),39)="Y","Prep and paint "&amp;INDEX(FILTER(INPUT_Rooms!$M$4:$M$83, INPUT_Rooms!$A$4:$A$83=$B$3),39)&amp;" coat(s) on "&amp;A44&amp;" walls.", ""),IF(INDEX(FILTER(INPUT_Rooms!$O$4:$O$83, INPUT_Rooms!$A$4:$A$83=$B$3),39)="Y","Prep and paint "&amp;INDEX(FILTER(INPUT_Rooms!$Q$4:$Q$83, INPUT_Rooms!$A$4:$A$83=$B$3),39)&amp;" coat(s) on "&amp;A44&amp;" ceilings.", ""),IF(INDEX(FILTER(INPUT_Rooms!$T$4:$T$83, INPUT_Rooms!$A$4:$A$83=$B$3),39)="Y","Prep and paint "&amp;INDEX(FILTER(INPUT_Rooms!$V$4:$V$83, INPUT_Rooms!$A$4:$A$83=$B$3),39)&amp;" coat(s) on "&amp;A44&amp;" trim ("&amp;TEXTJOIN(", ",TRUE,IF(INDEX(FILTER(INPUT_Rooms!$X$4:$X$83, INPUT_Rooms!$A$4:$A$83=$B$3),39)="Y","base",""),IF(INDEX(FILTER(INPUT_Rooms!$Y$4:$Y$83, INPUT_Rooms!$A$4:$A$83=$B$3),39)="Y","crown",""),IF(INDEX(FILTER(INPUT_Rooms!$Z$4:$Z$83, INPUT_Rooms!$A$4:$A$83=$B$3),39)="Y","window casing",""),IF(INDEX(FILTER(INPUT_Rooms!$AA$4:$AA$83, INPUT_Rooms!$A$4:$A$83=$B$3),39)="Y","door casing",""),IF(INDEX(FILTER(INPUT_Rooms!$AB$4:$AB$83, INPUT_Rooms!$A$4:$A$83=$B$3),39)="Y","doors",""))&amp;").", "")))</f><v></v></c></row><row r="45"><c r="A45" s="6"><f>IFERROR(INDEX(FILTER(INPUT_Rooms!$C$4:$C$83, INPUT_Rooms!$A$4:$A$83=$B$3), 40), "")</f><v></v></c><c r="B45" s="6"><f>IF(A45="","",TEXTJOIN(" ",TRUE,IF(INDEX(FILTER(INPUT_Rooms!$K$4:$K$83, INPUT_Rooms!$A$4:$A$83=$B$3),40)="Y","Prep and paint "&amp;INDEX(FILTER(INPUT_Rooms!$M$4:$M$83, INPUT_Rooms!$A$4:$A$83=$B$3),40)&amp;" coat(s) on "&amp;A45&amp;" walls.", ""),IF(INDEX(FILTER(INPUT_Rooms!$O$4:$O$83, INPUT_Rooms!$A$4:$A$83=$B$3),40)="Y","Prep and paint "&amp;INDEX(FILTER(INPUT_Rooms!$Q$4:$Q$83, INPUT_Rooms!$A$4:$A$83=$B$3),40)&amp;" coat(s) on "&amp;A45&amp;" ceilings.", ""),IF(INDEX(FILTER(INPUT_Rooms!$T$4:$T$83, INPUT_Rooms!$A$4:$A$83=$B$3),40)="Y","Prep and paint "&amp;INDEX(FILTER(INPUT_Rooms!$V$4:$V$83, INPUT_Rooms!$A$4:$A$83=$B$3),40)&amp;" coat(s) on "&amp;A45&amp;" trim ("&amp;TEXTJOIN(", ",TRUE,IF(INDEX(FILTER(INPUT_Rooms!$X$4:$X$83, INPUT_Rooms!$A$4:$A$83=$B$3),40)="Y","base",""),IF(INDEX(FILTER(INPUT_Rooms!$Y$4:$Y$83, INPUT_Rooms!$A$4:$A$83=$B$3),40)="Y","crown",""),IF(INDEX(FILTER(INPUT_Rooms!$Z$4:$Z$83, INPUT_Rooms!$A$4:$A$83=$B$3),40)="Y","window casing",""),IF(INDEX(FILTER(INPUT_Rooms!$AA$4:$AA$83, INPUT_Rooms!$A$4:$A$83=$B$3),40)="Y","door casing",""),IF(INDEX(FILTER(INPUT_Rooms!$AB$4:$AB$83, INPUT_Rooms!$A$4:$A$83=$B$3),40)="Y","doors",""))&amp;").", "")))</f><v></v></c></row><row r="46"><c r="A46" s="6"><f>IFERROR(INDEX(FILTER(INPUT_Rooms!$C$4:$C$83, INPUT_Rooms!$A$4:$A$83=$B$3), 41), "")</f><v></v></c><c r="B46" s="6"><f>IF(A46="","",TEXTJOIN(" ",TRUE,IF(INDEX(FILTER(INPUT_Rooms!$K$4:$K$83, INPUT_Rooms!$A$4:$A$83=$B$3),41)="Y","Prep and paint "&amp;INDEX(FILTER(INPUT_Rooms!$M$4:$M$83, INPUT_Rooms!$A$4:$A$83=$B$3),41)&amp;" coat(s) on "&amp;A46&amp;" walls.", ""),IF(INDEX(FILTER(INPUT_Rooms!$O$4:$O$83, INPUT_Rooms!$A$4:$A$83=$B$3),41)="Y","Prep and paint "&amp;INDEX(FILTER(INPUT_Rooms!$Q$4:$Q$83, INPUT_Rooms!$A$4:$A$83=$B$3),41)&amp;" coat(s) on "&amp;A46&amp;" ceilings.", ""),IF(INDEX(FILTER(INPUT_Rooms!$T$4:$T$83, INPUT_Rooms!$A$4:$A$83=$B$3),41)="Y","Prep and paint "&amp;INDEX(FILTER(INPUT_Rooms!$V$4:$V$83, INPUT_Rooms!$A$4:$A$83=$B$3),41)&amp;" coat(s) on "&amp;A46&amp;" trim ("&amp;TEXTJOIN(", ",TRUE,IF(INDEX(FILTER(INPUT_Rooms!$X$4:$X$83, INPUT_Rooms!$A$4:$A$83=$B$3),41)="Y","base",""),IF(INDEX(FILTER(INPUT_Rooms!$Y$4:$Y$83, INPUT_Rooms!$A$4:$A$83=$B$3),41)="Y","crown",""),IF(INDEX(FILTER(INPUT_Rooms!$Z$4:$Z$83, INPUT_Rooms!$A$4:$A$83=$B$3),41)="Y","window casing",""),IF(INDEX(FILTER(INPUT_Rooms!$AA$4:$AA$83, INPUT_Rooms!$A$4:$A$83=$B$3),41)="Y","door casing",""),IF(INDEX(FILTER(INPUT_Rooms!$AB$4:$AB$83, INPUT_Rooms!$A$4:$A$83=$B$3),41)="Y","doors",""))&amp;").", "")))</f><v></v></c></row><row r="47"><c r="A47" s="6"><f>IFERROR(INDEX(FILTER(INPUT_Rooms!$C$4:$C$83, INPUT_Rooms!$A$4:$A$83=$B$3), 42), "")</f><v></v></c><c r="B47" s="6"><f>IF(A47="","",TEXTJOIN(" ",TRUE,IF(INDEX(FILTER(INPUT_Rooms!$K$4:$K$83, INPUT_Rooms!$A$4:$A$83=$B$3),42)="Y","Prep and paint "&amp;INDEX(FILTER(INPUT_Rooms!$M$4:$M$83, INPUT_Rooms!$A$4:$A$83=$B$3),42)&amp;" coat(s) on "&amp;A47&amp;" walls.", ""),IF(INDEX(FILTER(INPUT_Rooms!$O$4:$O$83, INPUT_Rooms!$A$4:$A$83=$B$3),42)="Y","Prep and paint "&amp;INDEX(FILTER(INPUT_Rooms!$Q$4:$Q$83, INPUT_Rooms!$A$4:$A$83=$B$3),42)&amp;" coat(s) on "&amp;A47&amp;" ceilings.", ""),IF(INDEX(FILTER(INPUT_Rooms!$T$4:$T$83, INPUT_Rooms!$A$4:$A$83=$B$3),42)="Y","Prep and paint "&amp;INDEX(FILTER(INPUT_Rooms!$V$4:$V$83, INPUT_Rooms!$A$4:$A$83=$B$3),42)&amp;" coat(s) on "&amp;A47&amp;" trim ("&amp;TEXTJOIN(", ",TRUE,IF(INDEX(FILTER(INPUT_Rooms!$X$4:$X$83, INPUT_Rooms!$A$4:$A$83=$B$3),42)="Y","base",""),IF(INDEX(FILTER(INPUT_Rooms!$Y$4:$Y$83, INPUT_Rooms!$A$4:$A$83=$B$3),42)="Y","crown",""),IF(INDEX(FILTER(INPUT_Rooms!$Z$4:$Z$83, INPUT_Rooms!$A$4:$A$83=$B$3),42)="Y","window casing",""),IF(INDEX(FILTER(INPUT_Rooms!$AA$4:$AA$83, INPUT_Rooms!$A$4:$A$83=$B$3),42)="Y","door casing",""),IF(INDEX(FILTER(INPUT_Rooms!$AB$4:$AB$83, INPUT_Rooms!$A$4:$A$83=$B$3),42)="Y","doors",""))&amp;").", "")))</f><v></v></c></row><row r="48"><c r="A48" s="6"><f>IFERROR(INDEX(FILTER(INPUT_Rooms!$C$4:$C$83, INPUT_Rooms!$A$4:$A$83=$B$3), 43), "")</f><v></v></c><c r="B48" s="6"><f>IF(A48="","",TEXTJOIN(" ",TRUE,IF(INDEX(FILTER(INPUT_Rooms!$K$4:$K$83, INPUT_Rooms!$A$4:$A$83=$B$3),43)="Y","Prep and paint "&amp;INDEX(FILTER(INPUT_Rooms!$M$4:$M$83, INPUT_Rooms!$A$4:$A$83=$B$3),43)&amp;" coat(s) on "&amp;A48&amp;" walls.", ""),IF(INDEX(FILTER(INPUT_Rooms!$O$4:$O$83, INPUT_Rooms!$A$4:$A$83=$B$3),43)="Y","Prep and paint "&amp;INDEX(FILTER(INPUT_Rooms!$Q$4:$Q$83, INPUT_Rooms!$A$4:$A$83=$B$3),43)&amp;" coat(s) on "&amp;A48&amp;" ceilings.", ""),IF(INDEX(FILTER(INPUT_Rooms!$T$4:$T$83, INPUT_Rooms!$A$4:$A$83=$B$3),43)="Y","Prep and paint "&amp;INDEX(FILTER(INPUT_Rooms!$V$4:$V$83, INPUT_Rooms!$A$4:$A$83=$B$3),43)&amp;" coat(s) on "&amp;A48&amp;" trim ("&amp;TEXTJOIN(", ",TRUE,IF(INDEX(FILTER(INPUT_Rooms!$X$4:$X$83, INPUT_Rooms!$A$4:$A$83=$B$3),43)="Y","base",""),IF(INDEX(FILTER(INPUT_Rooms!$Y$4:$Y$83, INPUT_Rooms!$A$4:$A$83=$B$3),43)="Y","crown",""),IF(INDEX(FILTER(INPUT_Rooms!$Z$4:$Z$83, INPUT_Rooms!$A$4:$A$83=$B$3),43)="Y","window casing",""),IF(INDEX(FILTER(INPUT_Rooms!$AA$4:$AA$83, INPUT_Rooms!$A$4:$A$83=$B$3),43)="Y","door casing",""),IF(INDEX(FILTER(INPUT_Rooms!$AB$4:$AB$83, INPUT_Rooms!$A$4:$A$83=$B$3),43)="Y","doors",""))&amp;").", "")))</f><v></v></c></row><row r="49"><c r="A49" s="6"><f>IFERROR(INDEX(FILTER(INPUT_Rooms!$C$4:$C$83, INPUT_Rooms!$A$4:$A$83=$B$3), 44), "")</f><v></v></c><c r="B49" s="6"><f>IF(A49="","",TEXTJOIN(" ",TRUE,IF(INDEX(FILTER(INPUT_Rooms!$K$4:$K$83, INPUT_Rooms!$A$4:$A$83=$B$3),44)="Y","Prep and paint "&amp;INDEX(FILTER(INPUT_Rooms!$M$4:$M$83, INPUT_Rooms!$A$4:$A$83=$B$3),44)&amp;" coat(s) on "&amp;A49&amp;" walls.", ""),IF(INDEX(FILTER(INPUT_Rooms!$O$4:$O$83, INPUT_Rooms!$A$4:$A$83=$B$3),44)="Y","Prep and paint "&amp;INDEX(FILTER(INPUT_Rooms!$Q$4:$Q$83, INPUT_Rooms!$A$4:$A$83=$B$3),44)&amp;" coat(s) on "&amp;A49&amp;" ceilings.", ""),IF(INDEX(FILTER(INPUT_Rooms!$T$4:$T$83, INPUT_Rooms!$A$4:$A$83=$B$3),44)="Y","Prep and paint "&amp;INDEX(FILTER(INPUT_Rooms!$V$4:$V$83, INPUT_Rooms!$A$4:$A$83=$B$3),44)&amp;" coat(s) on "&amp;A49&amp;" trim ("&amp;TEXTJOIN(", ",TRUE,IF(INDEX(FILTER(INPUT_Rooms!$X$4:$X$83, INPUT_Rooms!$A$4:$A$83=$B$3),44)="Y","base",""),IF(INDEX(FILTER(INPUT_Rooms!$Y$4:$Y$83, INPUT_Rooms!$A$4:$A$83=$B$3),44)="Y","crown",""),IF(INDEX(FILTER(INPUT_Rooms!$Z$4:$Z$83, INPUT_Rooms!$A$4:$A$83=$B$3),44)="Y","window casing",""),IF(INDEX(FILTER(INPUT_Rooms!$AA$4:$AA$83, INPUT_Rooms!$A$4:$A$83=$B$3),44)="Y","door casing",""),IF(INDEX(FILTER(INPUT_Rooms!$AB$4:$AB$83, INPUT_Rooms!$A$4:$A$83=$B$3),44)="Y","doors",""))&amp;").", "")))</f><v></v></c></row><row r="50"><c r="A50" s="6"><f>IFERROR(INDEX(FILTER(INPUT_Rooms!$C$4:$C$83, INPUT_Rooms!$A$4:$A$83=$B$3), 45), "")</f><v></v></c><c r="B50" s="6"><f>IF(A50="","",TEXTJOIN(" ",TRUE,IF(INDEX(FILTER(INPUT_Rooms!$K$4:$K$83, INPUT_Rooms!$A$4:$A$83=$B$3),45)="Y","Prep and paint "&amp;INDEX(FILTER(INPUT_Rooms!$M$4:$M$83, INPUT_Rooms!$A$4:$A$83=$B$3),45)&amp;" coat(s) on "&amp;A50&amp;" walls.", ""),IF(INDEX(FILTER(INPUT_Rooms!$O$4:$O$83, INPUT_Rooms!$A$4:$A$83=$B$3),45)="Y","Prep and paint "&amp;INDEX(FILTER(INPUT_Rooms!$Q$4:$Q$83, INPUT_Rooms!$A$4:$A$83=$B$3),45)&amp;" coat(s) on "&amp;A50&amp;" ceilings.", ""),IF(INDEX(FILTER(INPUT_Rooms!$T$4:$T$83, INPUT_Rooms!$A$4:$A$83=$B$3),45)="Y","Prep and paint "&amp;INDEX(FILTER(INPUT_Rooms!$V$4:$V$83, INPUT_Rooms!$A$4:$A$83=$B$3),45)&amp;" coat(s) on "&amp;A50&amp;" trim ("&amp;TEXTJOIN(", ",TRUE,IF(INDEX(FILTER(INPUT_Rooms!$X$4:$X$83, INPUT_Rooms!$A$4:$A$83=$B$3),45)="Y","base",""),IF(INDEX(FILTER(INPUT_Rooms!$Y$4:$Y$83, INPUT_Rooms!$A$4:$A$83=$B$3),45)="Y","crown",""),IF(INDEX(FILTER(INPUT_Rooms!$Z$4:$Z$83, INPUT_Rooms!$A$4:$A$83=$B$3),45)="Y","window casing",""),IF(INDEX(FILTER(INPUT_Rooms!$AA$4:$AA$83, INPUT_Rooms!$A$4:$A$83=$B$3),45)="Y","door casing",""),IF(INDEX(FILTER(INPUT_Rooms!$AB$4:$AB$83, INPUT_Rooms!$A$4:$A$83=$B$3),45)="Y","doors",""))&amp;").", "")))</f><v></v></c></row><row r="51"><c r="A51" s="6"><f>IFERROR(INDEX(FILTER(INPUT_Rooms!$C$4:$C$83, INPUT_Rooms!$A$4:$A$83=$B$3), 46), "")</f><v></v></c><c r="B51" s="6"><f>IF(A51="","",TEXTJOIN(" ",TRUE,IF(INDEX(FILTER(INPUT_Rooms!$K$4:$K$83, INPUT_Rooms!$A$4:$A$83=$B$3),46)="Y","Prep and paint "&amp;INDEX(FILTER(INPUT_Rooms!$M$4:$M$83, INPUT_Rooms!$A$4:$A$83=$B$3),46)&amp;" coat(s) on "&amp;A51&amp;" walls.", ""),IF(INDEX(FILTER(INPUT_Rooms!$O$4:$O$83, INPUT_Rooms!$A$4:$A$83=$B$3),46)="Y","Prep and paint "&amp;INDEX(FILTER(INPUT_Rooms!$Q$4:$Q$83, INPUT_Rooms!$A$4:$A$83=$B$3),46)&amp;" coat(s) on "&amp;A51&amp;" ceilings.", ""),IF(INDEX(FILTER(INPUT_Rooms!$T$4:$T$83, INPUT_Rooms!$A$4:$A$83=$B$3),46)="Y","Prep and paint "&amp;INDEX(FILTER(INPUT_Rooms!$V$4:$V$83, INPUT_Rooms!$A$4:$A$83=$B$3),46)&amp;" coat(s) on "&amp;A51&amp;" trim ("&amp;TEXTJOIN(", ",TRUE,IF(INDEX(FILTER(INPUT_Rooms!$X$4:$X$83, INPUT_Rooms!$A$4:$A$83=$B$3),46)="Y","base",""),IF(INDEX(FILTER(INPUT_Rooms!$Y$4:$Y$83, INPUT_Rooms!$A$4:$A$83=$B$3),46)="Y","crown",""),IF(INDEX(FILTER(INPUT_Rooms!$Z$4:$Z$83, INPUT_Rooms!$A$4:$A$83=$B$3),46)="Y","window casing",""),IF(INDEX(FILTER(INPUT_Rooms!$AA$4:$AA$83, INPUT_Rooms!$A$4:$A$83=$B$3),46)="Y","door casing",""),IF(INDEX(FILTER(INPUT_Rooms!$AB$4:$AB$83, INPUT_Rooms!$A$4:$A$83=$B$3),46)="Y","doors",""))&amp;").", "")))</f><v></v></c></row><row r="52"><c r="A52" s="6"><f>IFERROR(INDEX(FILTER(INPUT_Rooms!$C$4:$C$83, INPUT_Rooms!$A$4:$A$83=$B$3), 47), "")</f><v></v></c><c r="B52" s="6"><f>IF(A52="","",TEXTJOIN(" ",TRUE,IF(INDEX(FILTER(INPUT_Rooms!$K$4:$K$83, INPUT_Rooms!$A$4:$A$83=$B$3),47)="Y","Prep and paint "&amp;INDEX(FILTER(INPUT_Rooms!$M$4:$M$83, INPUT_Rooms!$A$4:$A$83=$B$3),47)&amp;" coat(s) on "&amp;A52&amp;" walls.", ""),IF(INDEX(FILTER(INPUT_Rooms!$O$4:$O$83, INPUT_Rooms!$A$4:$A$83=$B$3),47)="Y","Prep and paint "&amp;INDEX(FILTER(INPUT_Rooms!$Q$4:$Q$83, INPUT_Rooms!$A$4:$A$83=$B$3),47)&amp;" coat(s) on "&amp;A52&amp;" ceilings.", ""),IF(INDEX(FILTER(INPUT_Rooms!$T$4:$T$83, INPUT_Rooms!$A$4:$A$83=$B$3),47)="Y","Prep and paint "&amp;INDEX(FILTER(INPUT_Rooms!$V$4:$V$83, INPUT_Rooms!$A$4:$A$83=$B$3),47)&amp;" coat(s) on "&amp;A52&amp;" trim ("&amp;TEXTJOIN(", ",TRUE,IF(INDEX(FILTER(INPUT_Rooms!$X$4:$X$83, INPUT_Rooms!$A$4:$A$83=$B$3),47)="Y","base",""),IF(INDEX(FILTER(INPUT_Rooms!$Y$4:$Y$83, INPUT_Rooms!$A$4:$A$83=$B$3),47)="Y","crown",""),IF(INDEX(FILTER(INPUT_Rooms!$Z$4:$Z$83, INPUT_Rooms!$A$4:$A$83=$B$3),47)="Y","window casing",""),IF(INDEX(FILTER(INPUT_Rooms!$AA$4:$AA$83, INPUT_Rooms!$A$4:$A$83=$B$3),47)="Y","door casing",""),IF(INDEX(FILTER(INPUT_Rooms!$AB$4:$AB$83, INPUT_Rooms!$A$4:$A$83=$B$3),47)="Y","doors",""))&amp;").", "")))</f><v></v></c></row><row r="53"><c r="A53" s="6"><f>IFERROR(INDEX(FILTER(INPUT_Rooms!$C$4:$C$83, INPUT_Rooms!$A$4:$A$83=$B$3), 48), "")</f><v></v></c><c r="B53" s="6"><f>IF(A53="","",TEXTJOIN(" ",TRUE,IF(INDEX(FILTER(INPUT_Rooms!$K$4:$K$83, INPUT_Rooms!$A$4:$A$83=$B$3),48)="Y","Prep and paint "&amp;INDEX(FILTER(INPUT_Rooms!$M$4:$M$83, INPUT_Rooms!$A$4:$A$83=$B$3),48)&amp;" coat(s) on "&amp;A53&amp;" walls.", ""),IF(INDEX(FILTER(INPUT_Rooms!$O$4:$O$83, INPUT_Rooms!$A$4:$A$83=$B$3),48)="Y","Prep and paint "&amp;INDEX(FILTER(INPUT_Rooms!$Q$4:$Q$83, INPUT_Rooms!$A$4:$A$83=$B$3),48)&amp;" coat(s) on "&amp;A53&amp;" ceilings.", ""),IF(INDEX(FILTER(INPUT_Rooms!$T$4:$T$83, INPUT_Rooms!$A$4:$A$83=$B$3),48)="Y","Prep and paint "&amp;INDEX(FILTER(INPUT_Rooms!$V$4:$V$83, INPUT_Rooms!$A$4:$A$83=$B$3),48)&amp;" coat(s) on "&amp;A53&amp;" trim ("&amp;TEXTJOIN(", ",TRUE,IF(INDEX(FILTER(INPUT_Rooms!$X$4:$X$83, INPUT_Rooms!$A$4:$A$83=$B$3),48)="Y","base",""),IF(INDEX(FILTER(INPUT_Rooms!$Y$4:$Y$83, INPUT_Rooms!$A$4:$A$83=$B$3),48)="Y","crown",""),IF(INDEX(FILTER(INPUT_Rooms!$Z$4:$Z$83, INPUT_Rooms!$A$4:$A$83=$B$3),48)="Y","window casing",""),IF(INDEX(FILTER(INPUT_Rooms!$AA$4:$AA$83, INPUT_Rooms!$A$4:$A$83=$B$3),48)="Y","door casing",""),IF(INDEX(FILTER(INPUT_Rooms!$AB$4:$AB$83, INPUT_Rooms!$A$4:$A$83=$B$3),48)="Y","doors",""))&amp;").", "")))</f><v></v></c></row><row r="54"><c r="A54" s="6"><f>IFERROR(INDEX(FILTER(INPUT_Rooms!$C$4:$C$83, INPUT_Rooms!$A$4:$A$83=$B$3), 49), "")</f><v></v></c><c r="B54" s="6"><f>IF(A54="","",TEXTJOIN(" ",TRUE,IF(INDEX(FILTER(INPUT_Rooms!$K$4:$K$83, INPUT_Rooms!$A$4:$A$83=$B$3),49)="Y","Prep and paint "&amp;INDEX(FILTER(INPUT_Rooms!$M$4:$M$83, INPUT_Rooms!$A$4:$A$83=$B$3),49)&amp;" coat(s) on "&amp;A54&amp;" walls.", ""),IF(INDEX(FILTER(INPUT_Rooms!$O$4:$O$83, INPUT_Rooms!$A$4:$A$83=$B$3),49)="Y","Prep and paint "&amp;INDEX(FILTER(INPUT_Rooms!$Q$4:$Q$83, INPUT_Rooms!$A$4:$A$83=$B$3),49)&amp;" coat(s) on "&amp;A54&amp;" ceilings.", ""),IF(INDEX(FILTER(INPUT_Rooms!$T$4:$T$83, INPUT_Rooms!$A$4:$A$83=$B$3),49)="Y","Prep and paint "&amp;INDEX(FILTER(INPUT_Rooms!$V$4:$V$83, INPUT_Rooms!$A$4:$A$83=$B$3),49)&amp;" coat(s) on "&amp;A54&amp;" trim ("&amp;TEXTJOIN(", ",TRUE,IF(INDEX(FILTER(INPUT_Rooms!$X$4:$X$83, INPUT_Rooms!$A$4:$A$83=$B$3),49)="Y","base",""),IF(INDEX(FILTER(INPUT_Rooms!$Y$4:$Y$83, INPUT_Rooms!$A$4:$A$83=$B$3),49)="Y","crown",""),IF(INDEX(FILTER(INPUT_Rooms!$Z$4:$Z$83, INPUT_Rooms!$A$4:$A$83=$B$3),49)="Y","window casing",""),IF(INDEX(FILTER(INPUT_Rooms!$AA$4:$AA$83, INPUT_Rooms!$A$4:$A$83=$B$3),49)="Y","door casing",""),IF(INDEX(FILTER(INPUT_Rooms!$AB$4:$AB$83, INPUT_Rooms!$A$4:$A$83=$B$3),49)="Y","doors",""))&amp;").", "")))</f><v></v></c></row><row r="55"><c r="A55" s="6"><f>IFERROR(INDEX(FILTER(INPUT_Rooms!$C$4:$C$83, INPUT_Rooms!$A$4:$A$83=$B$3), 50), "")</f><v></v></c><c r="B55" s="6"><f>IF(A55="","",TEXTJOIN(" ",TRUE,IF(INDEX(FILTER(INPUT_Rooms!$K$4:$K$83, INPUT_Rooms!$A$4:$A$83=$B$3),50)="Y","Prep and paint "&amp;INDEX(FILTER(INPUT_Rooms!$M$4:$M$83, INPUT_Rooms!$A$4:$A$83=$B$3),50)&amp;" coat(s) on "&amp;A55&amp;" walls.", ""),IF(INDEX(FILTER(INPUT_Rooms!$O$4:$O$83, INPUT_Rooms!$A$4:$A$83=$B$3),50)="Y","Prep and paint "&amp;INDEX(FILTER(INPUT_Rooms!$Q$4:$Q$83, INPUT_Rooms!$A$4:$A$83=$B$3),50)&amp;" coat(s) on "&amp;A55&amp;" ceilings.", ""),IF(INDEX(FILTER(INPUT_Rooms!$T$4:$T$83, INPUT_Rooms!$A$4:$A$83=$B$3),50)="Y","Prep and paint "&amp;INDEX(FILTER(INPUT_Rooms!$V$4:$V$83, INPUT_Rooms!$A$4:$A$83=$B$3),50)&amp;" coat(s) on "&amp;A55&amp;" trim ("&amp;TEXTJOIN(", ",TRUE,IF(INDEX(FILTER(INPUT_Rooms!$X$4:$X$83, INPUT_Rooms!$A$4:$A$83=$B$3),50)="Y","base",""),IF(INDEX(FILTER(INPUT_Rooms!$Y$4:$Y$83, INPUT_Rooms!$A$4:$A$83=$B$3),50)="Y","crown",""),IF(INDEX(FILTER(INPUT_Rooms!$Z$4:$Z$83, INPUT_Rooms!$A$4:$A$83=$B$3),50)="Y","window casing",""),IF(INDEX(FILTER(INPUT_Rooms!$AA$4:$AA$83, INPUT_Rooms!$A$4:$A$83=$B$3),50)="Y","door casing",""),IF(INDEX(FILTER(INPUT_Rooms!$AB$4:$AB$83, INPUT_Rooms!$A$4:$A$83=$B$3),50)="Y","doors",""))&amp;").", "")))</f><v></v></c></row><row r="56"><c r="A56" s="6"><f>IFERROR(INDEX(FILTER(INPUT_Rooms!$C$4:$C$83, INPUT_Rooms!$A$4:$A$83=$B$3), 51), "")</f><v></v></c><c r="B56" s="6"><f>IF(A56="","",TEXTJOIN(" ",TRUE,IF(INDEX(FILTER(INPUT_Rooms!$K$4:$K$83, INPUT_Rooms!$A$4:$A$83=$B$3),51)="Y","Prep and paint "&amp;INDEX(FILTER(INPUT_Rooms!$M$4:$M$83, INPUT_Rooms!$A$4:$A$83=$B$3),51)&amp;" coat(s) on "&amp;A56&amp;" walls.", ""),IF(INDEX(FILTER(INPUT_Rooms!$O$4:$O$83, INPUT_Rooms!$A$4:$A$83=$B$3),51)="Y","Prep and paint "&amp;INDEX(FILTER(INPUT_Rooms!$Q$4:$Q$83, INPUT_Rooms!$A$4:$A$83=$B$3),51)&amp;" coat(s) on "&amp;A56&amp;" ceilings.", ""),IF(INDEX(FILTER(INPUT_Rooms!$T$4:$T$83, INPUT_Rooms!$A$4:$A$83=$B$3),51)="Y","Prep and paint "&amp;INDEX(FILTER(INPUT_Rooms!$V$4:$V$83, INPUT_Rooms!$A$4:$A$83=$B$3),51)&amp;" coat(s) on "&amp;A56&amp;" trim ("&amp;TEXTJOIN(", ",TRUE,IF(INDEX(FILTER(INPUT_Rooms!$X$4:$X$83, INPUT_Rooms!$A$4:$A$83=$B$3),51)="Y","base",""),IF(INDEX(FILTER(INPUT_Rooms!$Y$4:$Y$83, INPUT_Rooms!$A$4:$A$83=$B$3),51)="Y","crown",""),IF(INDEX(FILTER(INPUT_Rooms!$Z$4:$Z$83, INPUT_Rooms!$A$4:$A$83=$B$3),51)="Y","window casing",""),IF(INDEX(FILTER(INPUT_Rooms!$AA$4:$AA$83, INPUT_Rooms!$A$4:$A$83=$B$3),51)="Y","door casing",""),IF(INDEX(FILTER(INPUT_Rooms!$AB$4:$AB$83, INPUT_Rooms!$A$4:$A$83=$B$3),51)="Y","doors",""))&amp;").", "")))</f><v></v></c></row><row r="57"><c r="A57" s="6"><f>IFERROR(INDEX(FILTER(INPUT_Rooms!$C$4:$C$83, INPUT_Rooms!$A$4:$A$83=$B$3), 52), "")</f><v></v></c><c r="B57" s="6"><f>IF(A57="","",TEXTJOIN(" ",TRUE,IF(INDEX(FILTER(INPUT_Rooms!$K$4:$K$83, INPUT_Rooms!$A$4:$A$83=$B$3),52)="Y","Prep and paint "&amp;INDEX(FILTER(INPUT_Rooms!$M$4:$M$83, INPUT_Rooms!$A$4:$A$83=$B$3),52)&amp;" coat(s) on "&amp;A57&amp;" walls.", ""),IF(INDEX(FILTER(INPUT_Rooms!$O$4:$O$83, INPUT_Rooms!$A$4:$A$83=$B$3),52)="Y","Prep and paint "&amp;INDEX(FILTER(INPUT_Rooms!$Q$4:$Q$83, INPUT_Rooms!$A$4:$A$83=$B$3),52)&amp;" coat(s) on "&amp;A57&amp;" ceilings.", ""),IF(INDEX(FILTER(INPUT_Rooms!$T$4:$T$83, INPUT_Rooms!$A$4:$A$83=$B$3),52)="Y","Prep and paint "&amp;INDEX(FILTER(INPUT_Rooms!$V$4:$V$83, INPUT_Rooms!$A$4:$A$83=$B$3),52)&amp;" coat(s) on "&amp;A57&amp;" trim ("&amp;TEXTJOIN(", ",TRUE,IF(INDEX(FILTER(INPUT_Rooms!$X$4:$X$83, INPUT_Rooms!$A$4:$A$83=$B$3),52)="Y","base",""),IF(INDEX(FILTER(INPUT_Rooms!$Y$4:$Y$83, INPUT_Rooms!$A$4:$A$83=$B$3),52)="Y","crown",""),IF(INDEX(FILTER(INPUT_Rooms!$Z$4:$Z$83, INPUT_Rooms!$A$4:$A$83=$B$3),52)="Y","window casing",""),IF(INDEX(FILTER(INPUT_Rooms!$AA$4:$AA$83, INPUT_Rooms!$A$4:$A$83=$B$3),52)="Y","door casing",""),IF(INDEX(FILTER(INPUT_Rooms!$AB$4:$AB$83, INPUT_Rooms!$A$4:$A$83=$B$3),52)="Y","doors",""))&amp;").", "")))</f><v></v></c></row><row r="58"><c r="A58" s="6"><f>IFERROR(INDEX(FILTER(INPUT_Rooms!$C$4:$C$83, INPUT_Rooms!$A$4:$A$83=$B$3), 53), "")</f><v></v></c><c r="B58" s="6"><f>IF(A58="","",TEXTJOIN(" ",TRUE,IF(INDEX(FILTER(INPUT_Rooms!$K$4:$K$83, INPUT_Rooms!$A$4:$A$83=$B$3),53)="Y","Prep and paint "&amp;INDEX(FILTER(INPUT_Rooms!$M$4:$M$83, INPUT_Rooms!$A$4:$A$83=$B$3),53)&amp;" coat(s) on "&amp;A58&amp;" walls.", ""),IF(INDEX(FILTER(INPUT_Rooms!$O$4:$O$83, INPUT_Rooms!$A$4:$A$83=$B$3),53)="Y","Prep and paint "&amp;INDEX(FILTER(INPUT_Rooms!$Q$4:$Q$83, INPUT_Rooms!$A$4:$A$83=$B$3),53)&amp;" coat(s) on "&amp;A58&amp;" ceilings.", ""),IF(INDEX(FILTER(INPUT_Rooms!$T$4:$T$83, INPUT_Rooms!$A$4:$A$83=$B$3),53)="Y","Prep and paint "&amp;INDEX(FILTER(INPUT_Rooms!$V$4:$V$83, INPUT_Rooms!$A$4:$A$83=$B$3),53)&amp;" coat(s) on "&amp;A58&amp;" trim ("&amp;TEXTJOIN(", ",TRUE,IF(INDEX(FILTER(INPUT_Rooms!$X$4:$X$83, INPUT_Rooms!$A$4:$A$83=$B$3),53)="Y","base",""),IF(INDEX(FILTER(INPUT_Rooms!$Y$4:$Y$83, INPUT_Rooms!$A$4:$A$83=$B$3),53)="Y","crown",""),IF(INDEX(FILTER(INPUT_Rooms!$Z$4:$Z$83, INPUT_Rooms!$A$4:$A$83=$B$3),53)="Y","window casing",""),IF(INDEX(FILTER(INPUT_Rooms!$AA$4:$AA$83, INPUT_Rooms!$A$4:$A$83=$B$3),53)="Y","door casing",""),IF(INDEX(FILTER(INPUT_Rooms!$AB$4:$AB$83, INPUT_Rooms!$A$4:$A$83=$B$3),53)="Y","doors",""))&amp;").", "")))</f><v></v></c></row><row r="59"><c r="A59" s="6"><f>IFERROR(INDEX(FILTER(INPUT_Rooms!$C$4:$C$83, INPUT_Rooms!$A$4:$A$83=$B$3), 54), "")</f><v></v></c><c r="B59" s="6"><f>IF(A59="","",TEXTJOIN(" ",TRUE,IF(INDEX(FILTER(INPUT_Rooms!$K$4:$K$83, INPUT_Rooms!$A$4:$A$83=$B$3),54)="Y","Prep and paint "&amp;INDEX(FILTER(INPUT_Rooms!$M$4:$M$83, INPUT_Rooms!$A$4:$A$83=$B$3),54)&amp;" coat(s) on "&amp;A59&amp;" walls.", ""),IF(INDEX(FILTER(INPUT_Rooms!$O$4:$O$83, INPUT_Rooms!$A$4:$A$83=$B$3),54)="Y","Prep and paint "&amp;INDEX(FILTER(INPUT_Rooms!$Q$4:$Q$83, INPUT_Rooms!$A$4:$A$83=$B$3),54)&amp;" coat(s) on "&amp;A59&amp;" ceilings.", ""),IF(INDEX(FILTER(INPUT_Rooms!$T$4:$T$83, INPUT_Rooms!$A$4:$A$83=$B$3),54)="Y","Prep and paint "&amp;INDEX(FILTER(INPUT_Rooms!$V$4:$V$83, INPUT_Rooms!$A$4:$A$83=$B$3),54)&amp;" coat(s) on "&amp;A59&amp;" trim ("&amp;TEXTJOIN(", ",TRUE,IF(INDEX(FILTER(INPUT_Rooms!$X$4:$X$83, INPUT_Rooms!$A$4:$A$83=$B$3),54)="Y","base",""),IF(INDEX(FILTER(INPUT_Rooms!$Y$4:$Y$83, INPUT_Rooms!$A$4:$A$83=$B$3),54)="Y","crown",""),IF(INDEX(FILTER(INPUT_Rooms!$Z$4:$Z$83, INPUT_Rooms!$A$4:$A$83=$B$3),54)="Y","window casing",""),IF(INDEX(FILTER(INPUT_Rooms!$AA$4:$AA$83, INPUT_Rooms!$A$4:$A$83=$B$3),54)="Y","door casing",""),IF(INDEX(FILTER(INPUT_Rooms!$AB$4:$AB$83, INPUT_Rooms!$A$4:$A$83=$B$3),54)="Y","doors",""))&amp;").", "")))</f><v></v></c></row><row r="60"><c r="A60" s="6"><f>IFERROR(INDEX(FILTER(INPUT_Rooms!$C$4:$C$83, INPUT_Rooms!$A$4:$A$83=$B$3), 55), "")</f><v></v></c><c r="B60" s="6"><f>IF(A60="","",TEXTJOIN(" ",TRUE,IF(INDEX(FILTER(INPUT_Rooms!$K$4:$K$83, INPUT_Rooms!$A$4:$A$83=$B$3),55)="Y","Prep and paint "&amp;INDEX(FILTER(INPUT_Rooms!$M$4:$M$83, INPUT_Rooms!$A$4:$A$83=$B$3),55)&amp;" coat(s) on "&amp;A60&amp;" walls.", ""),IF(INDEX(FILTER(INPUT_Rooms!$O$4:$O$83, INPUT_Rooms!$A$4:$A$83=$B$3),55)="Y","Prep and paint "&amp;INDEX(FILTER(INPUT_Rooms!$Q$4:$Q$83, INPUT_Rooms!$A$4:$A$83=$B$3),55)&amp;" coat(s) on "&amp;A60&amp;" ceilings.", ""),IF(INDEX(FILTER(INPUT_Rooms!$T$4:$T$83, INPUT_Rooms!$A$4:$A$83=$B$3),55)="Y","Prep and paint "&amp;INDEX(FILTER(INPUT_Rooms!$V$4:$V$83, INPUT_Rooms!$A$4:$A$83=$B$3),55)&amp;" coat(s) on "&amp;A60&amp;" trim ("&amp;TEXTJOIN(", ",TRUE,IF(INDEX(FILTER(INPUT_Rooms!$X$4:$X$83, INPUT_Rooms!$A$4:$A$83=$B$3),55)="Y","base",""),IF(INDEX(FILTER(INPUT_Rooms!$Y$4:$Y$83, INPUT_Rooms!$A$4:$A$83=$B$3),55)="Y","crown",""),IF(INDEX(FILTER(INPUT_Rooms!$Z$4:$Z$83, INPUT_Rooms!$A$4:$A$83=$B$3),55)="Y","window casing",""),IF(INDEX(FILTER(INPUT_Rooms!$AA$4:$AA$83, INPUT_Rooms!$A$4:$A$83=$B$3),55)="Y","door casing",""),IF(INDEX(FILTER(INPUT_Rooms!$AB$4:$AB$83, INPUT_Rooms!$A$4:$A$83=$B$3),55)="Y","doors",""))&amp;").", "")))</f><v></v></c></row><row r="61"><c r="A61" s="6"><f>IFERROR(INDEX(FILTER(INPUT_Rooms!$C$4:$C$83, INPUT_Rooms!$A$4:$A$83=$B$3), 56), "")</f><v></v></c><c r="B61" s="6"><f>IF(A61="","",TEXTJOIN(" ",TRUE,IF(INDEX(FILTER(INPUT_Rooms!$K$4:$K$83, INPUT_Rooms!$A$4:$A$83=$B$3),56)="Y","Prep and paint "&amp;INDEX(FILTER(INPUT_Rooms!$M$4:$M$83, INPUT_Rooms!$A$4:$A$83=$B$3),56)&amp;" coat(s) on "&amp;A61&amp;" walls.", ""),IF(INDEX(FILTER(INPUT_Rooms!$O$4:$O$83, INPUT_Rooms!$A$4:$A$83=$B$3),56)="Y","Prep and paint "&amp;INDEX(FILTER(INPUT_Rooms!$Q$4:$Q$83, INPUT_Rooms!$A$4:$A$83=$B$3),56)&amp;" coat(s) on "&amp;A61&amp;" ceilings.", ""),IF(INDEX(FILTER(INPUT_Rooms!$T$4:$T$83, INPUT_Rooms!$A$4:$A$83=$B$3),56)="Y","Prep and paint "&amp;INDEX(FILTER(INPUT_Rooms!$V$4:$V$83, INPUT_Rooms!$A$4:$A$83=$B$3),56)&amp;" coat(s) on "&amp;A61&amp;" trim ("&amp;TEXTJOIN(", ",TRUE,IF(INDEX(FILTER(INPUT_Rooms!$X$4:$X$83, INPUT_Rooms!$A$4:$A$83=$B$3),56)="Y","base",""),IF(INDEX(FILTER(INPUT_Rooms!$Y$4:$Y$83, INPUT_Rooms!$A$4:$A$83=$B$3),56)="Y","crown",""),IF(INDEX(FILTER(INPUT_Rooms!$Z$4:$Z$83, INPUT_Rooms!$A$4:$A$83=$B$3),56)="Y","window casing",""),IF(INDEX(FILTER(INPUT_Rooms!$AA$4:$AA$83, INPUT_Rooms!$A$4:$A$83=$B$3),56)="Y","door casing",""),IF(INDEX(FILTER(INPUT_Rooms!$AB$4:$AB$83, INPUT_Rooms!$A$4:$A$83=$B$3),56)="Y","doors",""))&amp;").", "")))</f><v></v></c></row><row r="62"><c r="A62" s="6"><f>IFERROR(INDEX(FILTER(INPUT_Rooms!$C$4:$C$83, INPUT_Rooms!$A$4:$A$83=$B$3), 57), "")</f><v></v></c><c r="B62" s="6"><f>IF(A62="","",TEXTJOIN(" ",TRUE,IF(INDEX(FILTER(INPUT_Rooms!$K$4:$K$83, INPUT_Rooms!$A$4:$A$83=$B$3),57)="Y","Prep and paint "&amp;INDEX(FILTER(INPUT_Rooms!$M$4:$M$83, INPUT_Rooms!$A$4:$A$83=$B$3),57)&amp;" coat(s) on "&amp;A62&amp;" walls.", ""),IF(INDEX(FILTER(INPUT_Rooms!$O$4:$O$83, INPUT_Rooms!$A$4:$A$83=$B$3),57)="Y","Prep and paint "&amp;INDEX(FILTER(INPUT_Rooms!$Q$4:$Q$83, INPUT_Rooms!$A$4:$A$83=$B$3),57)&amp;" coat(s) on "&amp;A62&amp;" ceilings.", ""),IF(INDEX(FILTER(INPUT_Rooms!$T$4:$T$83, INPUT_Rooms!$A$4:$A$83=$B$3),57)="Y","Prep and paint "&amp;INDEX(FILTER(INPUT_Rooms!$V$4:$V$83, INPUT_Rooms!$A$4:$A$83=$B$3),57)&amp;" coat(s) on "&amp;A62&amp;" trim ("&amp;TEXTJOIN(", ",TRUE,IF(INDEX(FILTER(INPUT_Rooms!$X$4:$X$83, INPUT_Rooms!$A$4:$A$83=$B$3),57)="Y","base",""),IF(INDEX(FILTER(INPUT_Rooms!$Y$4:$Y$83, INPUT_Rooms!$A$4:$A$83=$B$3),57)="Y","crown",""),IF(INDEX(FILTER(INPUT_Rooms!$Z$4:$Z$83, INPUT_Rooms!$A$4:$A$83=$B$3),57)="Y","window casing",""),IF(INDEX(FILTER(INPUT_Rooms!$AA$4:$AA$83, INPUT_Rooms!$A$4:$A$83=$B$3),57)="Y","door casing",""),IF(INDEX(FILTER(INPUT_Rooms!$AB$4:$AB$83, INPUT_Rooms!$A$4:$A$83=$B$3),57)="Y","doors",""))&amp;").", "")))</f><v></v></c></row><row r="63"><c r="A63" s="6"><f>IFERROR(INDEX(FILTER(INPUT_Rooms!$C$4:$C$83, INPUT_Rooms!$A$4:$A$83=$B$3), 58), "")</f><v></v></c><c r="B63" s="6"><f>IF(A63="","",TEXTJOIN(" ",TRUE,IF(INDEX(FILTER(INPUT_Rooms!$K$4:$K$83, INPUT_Rooms!$A$4:$A$83=$B$3),58)="Y","Prep and paint "&amp;INDEX(FILTER(INPUT_Rooms!$M$4:$M$83, INPUT_Rooms!$A$4:$A$83=$B$3),58)&amp;" coat(s) on "&amp;A63&amp;" walls.", ""),IF(INDEX(FILTER(INPUT_Rooms!$O$4:$O$83, INPUT_Rooms!$A$4:$A$83=$B$3),58)="Y","Prep and paint "&amp;INDEX(FILTER(INPUT_Rooms!$Q$4:$Q$83, INPUT_Rooms!$A$4:$A$83=$B$3),58)&amp;" coat(s) on "&amp;A63&amp;" ceilings.", ""),IF(INDEX(FILTER(INPUT_Rooms!$T$4:$T$83, INPUT_Rooms!$A$4:$A$83=$B$3),58)="Y","Prep and paint "&amp;INDEX(FILTER(INPUT_Rooms!$V$4:$V$83, INPUT_Rooms!$A$4:$A$83=$B$3),58)&amp;" coat(s) on "&amp;A63&amp;" trim ("&amp;TEXTJOIN(", ",TRUE,IF(INDEX(FILTER(INPUT_Rooms!$X$4:$X$83, INPUT_Rooms!$A$4:$A$83=$B$3),58)="Y","base",""),IF(INDEX(FILTER(INPUT_Rooms!$Y$4:$Y$83, INPUT_Rooms!$A$4:$A$83=$B$3),58)="Y","crown",""),IF(INDEX(FILTER(INPUT_Rooms!$Z$4:$Z$83, INPUT_Rooms!$A$4:$A$83=$B$3),58)="Y","window casing",""),IF(INDEX(FILTER(INPUT_Rooms!$AA$4:$AA$83, INPUT_Rooms!$A$4:$A$83=$B$3),58)="Y","door casing",""),IF(INDEX(FILTER(INPUT_Rooms!$AB$4:$AB$83, INPUT_Rooms!$A$4:$A$83=$B$3),58)="Y","doors",""))&amp;").", "")))</f><v></v></c></row><row r="64"><c r="A64" s="6"><f>IFERROR(INDEX(FILTER(INPUT_Rooms!$C$4:$C$83, INPUT_Rooms!$A$4:$A$83=$B$3), 59), "")</f><v></v></c><c r="B64" s="6"><f>IF(A64="","",TEXTJOIN(" ",TRUE,IF(INDEX(FILTER(INPUT_Rooms!$K$4:$K$83, INPUT_Rooms!$A$4:$A$83=$B$3),59)="Y","Prep and paint "&amp;INDEX(FILTER(INPUT_Rooms!$M$4:$M$83, INPUT_Rooms!$A$4:$A$83=$B$3),59)&amp;" coat(s) on "&amp;A64&amp;" walls.", ""),IF(INDEX(FILTER(INPUT_Rooms!$O$4:$O$83, INPUT_Rooms!$A$4:$A$83=$B$3),59)="Y","Prep and paint "&amp;INDEX(FILTER(INPUT_Rooms!$Q$4:$Q$83, INPUT_Rooms!$A$4:$A$83=$B$3),59)&amp;" coat(s) on "&amp;A64&amp;" ceilings.", ""),IF(INDEX(FILTER(INPUT_Rooms!$T$4:$T$83, INPUT_Rooms!$A$4:$A$83=$B$3),59)="Y","Prep and paint "&amp;INDEX(FILTER(INPUT_Rooms!$V$4:$V$83, INPUT_Rooms!$A$4:$A$83=$B$3),59)&amp;" coat(s) on "&amp;A64&amp;" trim ("&amp;TEXTJOIN(", ",TRUE,IF(INDEX(FILTER(INPUT_Rooms!$X$4:$X$83, INPUT_Rooms!$A$4:$A$83=$B$3),59)="Y","base",""),IF(INDEX(FILTER(INPUT_Rooms!$Y$4:$Y$83, INPUT_Rooms!$A$4:$A$83=$B$3),59)="Y","crown",""),IF(INDEX(FILTER(INPUT_Rooms!$Z$4:$Z$83, INPUT_Rooms!$A$4:$A$83=$B$3),59)="Y","window casing",""),IF(INDEX(FILTER(INPUT_Rooms!$AA$4:$AA$83, INPUT_Rooms!$A$4:$A$83=$B$3),59)="Y","door casing",""),IF(INDEX(FILTER(INPUT_Rooms!$AB$4:$AB$83, INPUT_Rooms!$A$4:$A$83=$B$3),59)="Y","doors",""))&amp;").", "")))</f><v></v></c></row><row r="65"><c r="A65" s="6"><f>IFERROR(INDEX(FILTER(INPUT_Rooms!$C$4:$C$83, INPUT_Rooms!$A$4:$A$83=$B$3), 60), "")</f><v></v></c><c r="B65" s="6"><f>IF(A65="","",TEXTJOIN(" ",TRUE,IF(INDEX(FILTER(INPUT_Rooms!$K$4:$K$83, INPUT_Rooms!$A$4:$A$83=$B$3),60)="Y","Prep and paint "&amp;INDEX(FILTER(INPUT_Rooms!$M$4:$M$83, INPUT_Rooms!$A$4:$A$83=$B$3),60)&amp;" coat(s) on "&amp;A65&amp;" walls.", ""),IF(INDEX(FILTER(INPUT_Rooms!$O$4:$O$83, INPUT_Rooms!$A$4:$A$83=$B$3),60)="Y","Prep and paint "&amp;INDEX(FILTER(INPUT_Rooms!$Q$4:$Q$83, INPUT_Rooms!$A$4:$A$83=$B$3),60)&amp;" coat(s) on "&amp;A65&amp;" ceilings.", ""),IF(INDEX(FILTER(INPUT_Rooms!$T$4:$T$83, INPUT_Rooms!$A$4:$A$83=$B$3),60)="Y","Prep and paint "&amp;INDEX(FILTER(INPUT_Rooms!$V$4:$V$83, INPUT_Rooms!$A$4:$A$83=$B$3),60)&amp;" coat(s) on "&amp;A65&amp;" trim ("&amp;TEXTJOIN(", ",TRUE,IF(INDEX(FILTER(INPUT_Rooms!$X$4:$X$83, INPUT_Rooms!$A$4:$A$83=$B$3),60)="Y","base",""),IF(INDEX(FILTER(INPUT_Rooms!$Y$4:$Y$83, INPUT_Rooms!$A$4:$A$83=$B$3),60)="Y","crown",""),IF(INDEX(FILTER(INPUT_Rooms!$Z$4:$Z$83, INPUT_Rooms!$A$4:$A$83=$B$3),60)="Y","window casing",""),IF(INDEX(FILTER(INPUT_Rooms!$AA$4:$AA$83, INPUT_Rooms!$A$4:$A$83=$B$3),60)="Y","door casing",""),IF(INDEX(FILTER(INPUT_Rooms!$AB$4:$AB$83, INPUT_Rooms!$A$4:$A$83=$B$3),60)="Y","doors",""))&amp;").", "")))</f><v></v></c></row></sheetData><mergeCells count="1"><mergeCell ref="A1:H1"/></mergeCells><pageMargins left="0.75" right="0.75" top="1" bottom="1" header="0.5" footer="0.5"/></worksheet>